{"PVPC":[{"Dia":"28/07/2021","Hora":"00-01","PCB":"109,61","CYM":"109,61","COF2TD":"0,000115273608000000","PMHPCB":"96,29","PMHCYM":"96,29","SAHPCB":"4,64","SAHCYM":"4,64","FOMPCB":"0,03","FOMCYM":"0,03","FOSPCB":"0,17","FOSCYM":"0,17","INTPCB":"0,00","INTCYM":"0,00","PCAPPCB":"0,00","PCAPCYM":"0,00","TEUPCB":"6,00","TEUCYM":"6,00","CCVPCB":"2,48","CCVCYM":"2,48","EDSRPCB":"0,00","EDSRCYM":"0,00"},{"Dia":"28/07/2021","Hora":"01-02","PCB":"107,04","CYM":"107,04","COF2TD":"0,000096499509000000","PMHPCB":"92,57","PMHCYM":"92,57","SAHPCB":"5,83","SAHCYM":"5,83","FOMPCB":"0,03","FOMCYM":"0,03","FOSPCB":"0,17","FOSCYM":"0,17","INTPCB":"0,00","INTCYM":"0,00","PCAPPCB":"0,00","PCAPCYM":"0,00","TEUPCB":"6,00","TEUCYM":"6,00","CCVPCB":"2,44","CCVCYM":"2,44","EDSRPCB":"0,00","EDSRCYM":"0,00"},{"Dia":"28/07/2021","Hora":"02-03","PCB":"101,62","CYM":"101,62","COF2TD":"0,000085552992000000","PMHPCB":"86,89","PMHCYM":"86,89","SAHPCB":"6,16","SAHCYM":"6,16","FOMPCB":"0,03","FOMCYM":"0,03","FOSPCB":"0,17","FOSCYM":"0,17","INTPCB":"0,00","INTCYM":"0,00","PCAPPCB":"0,00","PCAPCYM":"0,00","TEUPCB":"6,00","TEUCYM":"6,00","CCVPCB":"2,36","CCVCYM":"2,36","EDSRPCB":"0,00","EDSRCYM":"0,00"},{"Dia":"28/07/2021","Hora":"03-04","PCB":"102,86","CYM":"102,86","COF2TD":"0,000079659172000000","PMHPCB":"89,41","PMHCYM":"89,41","SAHPCB":"4,87","SAHCYM":"4,87","FOMPCB":"0,03","FOMCYM":"0,03","FOSPCB":"0,17","FOSCYM":"0,17","INTPCB":"0,00","INTCYM":"0,00","PCAPPCB":"0,00","PCAPCYM":"0,00","TEUPCB":"6,00","TEUCYM":"6,00","CCVPCB":"2,38","CCVCYM":"2,38","EDSRPCB":"0,00","EDSRCYM":"0,00"},{"Dia":"28/07/2021","Hora":"04-05","PCB":"100,21","CYM":"100,21","COF2TD":"0,000076376555000000","PMHPCB":"86,55","PMHCYM":"86,55","SAHPCB":"5,12","SAHCYM":"5,12","FOMPCB":"0,03","FOMCYM":"0,03","FOSPCB":"0,17","FOSCYM":"0,17","INTPCB":"0,00","INTCYM":"0,00","PCAPPCB":"0,00","PCAPCYM":"0,00","TEUPCB":"6,00","TEUCYM":"6,00","CCVPCB":"2,34","CCVCYM":"2,34","EDSRPCB":"0,00","EDSRCYM":"0,00"},{"Dia":"28/07/2021","Hora":"05-06","PCB":"106,11","CYM":"106,11","COF2TD":"0,000075331334000000","PMHPCB":"93,11","PMHCYM":"93,11","SAHPCB":"4,36","SAHCYM":"4,36","FOMPCB":"0,03","FOMCYM":"0,03","FOSPCB":"0,17","FOSCYM":"0,17","INTPCB":"0,00","INTCYM":"0,00","PCAPPCB":"0,00","PCAPCYM":"0,00","TEUPCB":"6,00","TEUCYM":"6,00","CCVPCB":"2,43","CCVCYM":"2,43","EDSRPCB":"0,00","EDSRCYM":"0,00"},{"Dia":"28/07/2021","Hora":"06-07","PCB":"125,38","CYM":"125,38","COF2TD":"0,000077737214000000","PMHPCB":"112,68","PMHCYM":"112,68","SAHPCB":"3,80","SAHCYM":"3,80","FOMPCB":"0,03","FOMCYM":"0,03","FOSPCB":"0,17","FOSCYM":"0,17","INTPCB":"0,00","INTCYM":"0,00","PCAPPCB":"0,00","PCAPCYM":"0,00","TEUPCB":"6,00","TEUCYM":"6,00","CCVPCB":"2,71","CCVCYM":"2,71","EDSRPCB":"0,00","EDSRCYM":"0,00"},{"Dia":"28/07/2021","Hora":"07-08","PCB":"127,83","CYM":"127,83","COF2TD":"0,000082925940000000","PMHPCB":"115,71","PMHCYM":"115,71","SAHPCB":"3,19","SAHCYM":"3,19","FOMPCB":"0,03","FOMCYM":"0,03","FOSPCB":"0,17","FOSCYM":"0,17","INTPCB":"0,00","INTCYM":"0,00","PCAPPCB":"0,00","PCAPCYM":"0,00","TEUPCB":"6,00","TEUCYM":"6,00","CCVPCB":"2,74","CCVCYM":"2,74","EDSRPCB":"0,00","EDSRCYM":"0,00"},{"Dia":"28/07/2021","Hora":"08-09","PCB":"163,98","CYM":"163,98","COF2TD":"0,000096447729000000","PMHPCB":"116,60","PMHCYM":"116,60","SAHPCB":"2,34","SAHCYM":"2,34","FOMPCB":"0,03","FOMCYM":"0,03","FOSPCB":"0,16","FOSCYM":"0,16","INTPCB":"0,00","INTCYM":"0,00","PCAPPCB":"0,34","PCAPCYM":"0,34","TEUPCB":"41,77","TEUCYM":"41,77","CCVPCB":"2,74","CCVCYM":"2,74","EDSRPCB":"0,00","EDSRCYM":"0,00"},{"Dia":"28/07/2021","Hora":"09-10","PCB":"164,96","CYM":"164,96","COF2TD":"0,000110260403000000","PMHPCB":"118,18","PMHCYM":"118,18","SAHPCB":"1,74","SAHCYM":"1,74","FOMPCB":"0,03","FOMCYM":"0,03","FOSPCB":"0,16","FOSCYM":"0,16","INTPCB":"0,00","INTCYM":"0,00","PCAPPCB":"0,34","PCAPCYM":"0,34","TEUPCB":"41,77","TEUCYM":"41,77","CCVPCB":"2,75","CCVCYM":"2,75","EDSRPCB":"0,00","EDSRCYM":"0,00"},{"Dia":"28/07/2021","Hora":"10-11","PCB":"255,09","CYM":"161,60","COF2TD":"0,000121349733000000","PMHPCB":"115,06","PMHCYM":"114,66","SAHPCB":"1,96","SAHCYM":"1,95","FOMPCB":"0,03","FOMCYM":"0,03","FOSPCB":"0,16","FOSCYM":"0,16","INTPCB":"0,00","INTCYM":"0,00","PCAPPCB":"2,02","PCAPCYM":"0,34","TEUPCB":"133,12","TEUCYM":"41,77","CCVPCB":"2,73","CCVCYM":"2,69","EDSRPCB":"0,00","EDSRCYM":"0,00"},{"Dia":"28/07/2021","Hora":"11-12","PCB":"257,54","CYM":"257,54","COF2TD":"0,000126748162000000","PMHPCB":"117,46","PMHCYM":"117,46","SAHPCB":"1,99","SAHCYM":"1,99","FOMPCB":"0,03","FOMCYM":"0,03","FOSPCB":"0,16","FOSCYM":"0,16","INTPCB":"0,00","INTCYM":"0,00","PCAPPCB":"2,02","PCAPCYM":"2,02","TEUPCB":"133,12","TEUCYM":"133,12","CCVPCB":"2,76","CCVCYM":"2,76","EDSRPCB":"0,00","EDSRCYM":"0,00"},{"Dia":"28/07/2021","Hora":"12-13","PCB":"264,82","CYM":"264,82","COF2TD":"0,000133667026000000","PMHPCB":"124,82","PMHCYM":"124,82","SAHPCB":"1,78","SAHCYM":"1,78","FOMPCB":"0,03","FOMCYM":"0,03","FOSPCB":"0,16","FOSCYM":"0,16","INTPCB":"0,00","INTCYM":"0,00","PCAPPCB":"2,03","PCAPCYM":"2,03","TEUPCB":"133,12","TEUCYM":"133,12","CCVPCB":"2,88","CCVCYM":"2,88","EDSRPCB":"0,00","EDSRCYM":"0,00"},{"Dia":"28/07/2021","Hora":"13-14","PCB":"261,44","CYM":"261,44","COF2TD":"0,000144659881000000","PMHPCB":"121,30","PMHCYM":"121,30","SAHPCB":"1,96","SAHCYM":"1,96","FOMPCB":"0,03","FOMCYM":"0,03","FOSPCB":"0,16","FOSCYM":"0,16","INTPCB":"0,00","INTCYM":"0,00","PCAPPCB":"2,03","PCAPCYM":"2,03","TEUPCB":"133,12","TEUCYM":"133,12","CCVPCB":"2,83","CCVCYM":"2,83","EDSRPCB":"0,00","EDSRCYM":"0,00"},{"Dia":"28/07/2021","Hora":"14-15","PCB":"165,87","CYM":"259,37","COF2TD":"0,000148149875000000","PMHPCB":"118,81","PMHCYM":"119,22","SAHPCB":"2,00","SAHCYM":"2,01","FOMPCB":"0,03","FOMCYM":"0,03","FOSPCB":"0,16","FOSCYM":"0,16","INTPCB":"0,00","INTCYM":"0,00","PCAPPCB":"0,34","PCAPCYM":"2,03","TEUPCB":"41,77","TEUCYM":"133,12","CCVPCB":"2,76","CCVCYM":"2,80","EDSRPCB":"0,00","EDSRCYM":"0,00"},{"Dia":"28/07/2021","Hora":"15-16","PCB":"165,93","CYM":"165,93","COF2TD":"0,000142445687000000","PMHPCB":"118,89","PMHCYM":"118,89","SAHPCB":"1,97","SAHCYM":"1,97","FOMPCB":"0,03","FOMCYM":"0,03","FOSPCB":"0,16","FOSCYM":"0,16","INTPCB":"0,00","INTCYM":"0,00","PCAPPCB":"0,34","PCAPCYM":"0,34","TEUPCB":"41,77","TEUCYM":"41,77","CCVPCB":"2,76","CCVCYM":"2,76","EDSRPCB":"0,00","EDSRCYM":"0,00"},{"Dia":"28/07/2021","Hora":"16-17","PCB":"163,91","CYM":"163,91","COF2TD":"0,000139469413000000","PMHPCB":"116,86","PMHCYM":"116,86","SAHPCB":"2,01","SAHCYM":"2,01","FOMPCB":"0,03","FOMCYM":"0,03","FOSPCB":"0,16","FOSCYM":"0,16","INTPCB":"0,00","INTCYM":"0,00","PCAPPCB":"0,34","PCAPCYM":"0,34","TEUPCB":"41,77","TEUCYM":"41,77","CCVPCB":"2,73","CCVCYM":"2,73","EDSRPCB":"0,00","EDSRCYM":"0,00"},{"Dia":"28/07/2021","Hora":"17-18","PCB":"164,54","CYM":"164,54","COF2TD":"0,000140276867000000","PMHPCB":"117,52","PMHCYM":"117,52","SAHPCB":"1,98","SAHCYM":"1,98","FOMPCB":"0,03","FOMCYM":"0,03","FOSPCB":"0,16","FOSCYM":"0,16","INTPCB":"0,00","INTCYM":"0,00","PCAPPCB":"0,34","PCAPCYM":"0,34","TEUPCB":"41,77","TEUCYM":"41,77","CCVPCB":"2,74","CCVCYM":"2,74","EDSRPCB":"0,00","EDSRCYM":"0,00"},{"Dia":"28/07/2021","Hora":"18-19","PCB":"252,79","CYM":"159,41","COF2TD":"0,000140160159000000","PMHPCB":"112,44","PMHCYM":"112,14","SAHPCB":"2,30","SAHCYM":"2,30","FOMPCB":"0,03","FOMCYM":"0,03","FOSPCB":"0,17","FOSCYM":"0,16","INTPCB":"0,00","INTCYM":"0,00","PCAPPCB":"2,04","PCAPCYM":"0,34","TEUPCB":"133,12","TEUCYM":"41,77","CCVPCB":"2,70","CCVCYM":"2,67","EDSRPCB":"0,00","EDSRCYM":"0,00"},{"Dia":"28/07/2021","Hora":"19-20","PCB":"252,18","CYM":"252,18","COF2TD":"0,000138314105000000","PMHPCB":"111,06","PMHCYM":"111,06","SAHPCB":"3,06","SAHCYM":"3,06","FOMPCB":"0,03","FOMCYM":"0,03","FOSPCB":"0,17","FOSCYM":"0,17","INTPCB":"0,00","INTCYM":"0,00","PCAPPCB":"2,05","PCAPCYM":"2,05","TEUPCB":"133,12","TEUCYM":"133,12","CCVPCB":"2,70","CCVCYM":"2,70","EDSRPCB":"0,00","EDSRCYM":"0,00"},{"Dia":"28/07/2021","Hora":"20-21","PCB":"254,89","CYM":"254,89","COF2TD":"0,000139276309000000","PMHPCB":"114,02","PMHCYM":"114,02","SAHPCB":"2,75","SAHCYM":"2,75","FOMPCB":"0,03","FOMCYM":"0,03","FOSPCB":"0,17","FOSCYM":"0,17","INTPCB":"0,00","INTCYM":"0,00","PCAPPCB":"2,06","PCAPCYM":"2,06","TEUPCB":"133,12","TEUCYM":"133,12","CCVPCB":"2,75","CCVCYM":"2,75","EDSRPCB":"0,00","EDSRCYM":"0,00"},{"Dia":"28/07/2021","Hora":"21-22","PCB":"258,17","CYM":"258,17","COF2TD":"0,000150378469000000","PMHPCB":"117,02","PMHCYM":"117,02","SAHPCB":"2,97","SAHCYM":"2,97","FOMPCB":"0,03","FOMCYM":"0,03","FOSPCB":"0,17","FOSCYM":"0,17","INTPCB":"0,00","INTCYM":"0,00","PCAPPCB":"2,07","PCAPCYM":"2,07","TEUPCB":"133,12","TEUCYM":"133,12","CCVPCB":"2,80","CCVCYM":"2,80","EDSRPCB":"0,00","EDSRCYM":"0,00"},{"Dia":"28/07/2021","Hora":"22-23","PCB":"164,09","CYM":"257,62","COF2TD":"0,000157775317000000","PMHPCB":"116,03","PMHCYM":"116,43","SAHPCB":"3,00","SAHCYM":"3,01","FOMPCB":"0,03","FOMCYM":"0,03","FOSPCB":"0,17","FOSCYM":"0,17","INTPCB":"0,00","INTCYM":"0,00","PCAPPCB":"0,34","PCAPCYM":"2,07","TEUPCB":"41,77","TEUCYM":"133,12","CCVPCB":"2,75","CCVCYM":"2,79","EDSRPCB":"0,00","EDSRCYM":"0,00"},{"Dia":"28/07/2021","Hora":"23-24","PCB":"156,24","CYM":"156,24","COF2TD":"0,000140017630000000","PMHPCB":"107,84","PMHCYM":"107,84","SAHPCB":"3,44","SAHCYM":"3,44","FOMPCB":"0,03","FOMCYM":"0,03","FOSPCB":"0,17","FOSCYM":"0,17","INTPCB":"0,00","INTCYM":"0,00","PCAPPCB":"0,35","PCAPCYM":"0,35","TEUPCB":"41,77","TEUCYM":"41,77","CCVPCB":"2,64","CCVCYM":"2,64","EDSRPCB":"0,00","EDSRCYM":"0,00"}]}