[{"day":"18/02/2022","hour":0,"price":0.262,"zone":"valle"},{"day":"18/02/2022","hour":1,"price":0.258,"zone":"valle"},{"day":"18/02/2022","hour":2,"price":0.25,"zone":"valle"},{"day":"18/02/2022","hour":3,"price":0.238,"zone":"valle"},{"day":"18/02/2022","hour":4,"price":0.23,"zone":"valle"},{"day":"18/02/2022","hour":5,"price":0.229,"zone":"valle"},{"day":"18/02/2022","hour":6,"price":0.255,"zone":"valle"},{"day":"18/02/2022","hour":7,"price":0.264,"zone":"valle"},{"day":"18/02/2022","hour":8,"price":0.295,"zone":"llano"},{"day":"18/02/2022","hour":9,"price":0.289,"zone":"llano"},{"day":"18/02/2022","hour":10,"price":0.351,"zone":"punta"},{"day":"18/02/2022","hour":11,"price":0.345,"zone":"punta"},{"day":"18/02/2022","hour":12,"price":0.332,"zone":"punta"},{"day":"18/02/2022","hour":13,"price":0.323,"zone":"punta"},{"day":"18/02/2022","hour":14,"price":0.23,"zone":"llano"},{"day":"18/02/2022","hour":15,"price":0.224,"zone":"llano"},{"day":"18/02/2022","hour":16,"price":0.226,"zone":"llano"},{"day":"18/02/2022","hour":17,"price":0.23,"zone":"llano"},{"day":"18/02/2022","hour":18,"price":0.341,"zone":"punta"},{"day":"18/02/2022","hour":19,"price":0.352,"zone":"punta"},{"day":"18/02/2022","hour":20,"price":0.341,"zone":"punta"},{"day":"18/02/2022","hour":21,"price":0.324,"zone":"punta"},{"day":"18/02/2022","hour":22,"price":0.224,"zone":"llano"},{"day":"18/02/2022","hour":23,"price":0.217,"zone":"llano"}]