[{"year":"2022","month":"12","day":"26","hour":0,"price":0.0503,"pricemin":0.0503},{"year":"2022","month":"12","day":"26","hour":1,"price":0.03698,"pricemin":0.03698},{"year":"2022","month":"12","day":"26","hour":2,"price":0.030199999999999998,"pricemin":0.030199999999999998},{"year":"2022","month":"12","day":"26","hour":3,"price":0.0241,"pricemin":0.0241},{"year":"2022","month":"12","day":"26","hour":4,"price":0.024120000000000003,"pricemin":0.024120000000000003},{"year":"2022","month":"12","day":"26","hour":5,"price":0.02998,"pricemin":0.02998},{"year":"2022","month":"12","day":"26","hour":6,"price":0.032600000000000004,"pricemin":0.032600000000000004},{"year":"2022","month":"12","day":"26","hour":7,"price":0.04021,"pricemin":0.04021},{"year":"2022","month":"12","day":"26","hour":8,"price":0.04616,"pricemin":0.04616},{"year":"2022","month":"12","day":"26","hour":9,"price":0.05357,"pricemin":0.05357},{"year":"2022","month":"12","day":"26","hour":10,"price":0.0593,"pricemin":0.0593},{"year":"2022","month":"12","day":"26","hour":11,"price":0.059,"pricemin":0.059},{"year":"2022","month":"12","day":"26","hour":12,"price":0.0549,"pricemin":0.0549},{"year":"2022","month":"12","day":"26","hour":13,"price":0.055189999999999996,"pricemin":0.055189999999999996},{"year":"2022","month":"12","day":"26","hour":14,"price":0.0586,"pricemin":0.0586},{"year":"2022","month":"12","day":"26","hour":15,"price":0.06078,"pricemin":0.06078},{"year":"2022","month":"12","day":"26","hour":16,"price":0.08,"pricemin":0.08},{"year":"2022","month":"12","day":"26","hour":17,"price":0.126,"pricemin":0.126},{"year":"2022","month":"12","day":"26","hour":18,"price":0.16711,"pricemin":0.16711},{"year":"2022","month":"12","day":"26","hour":19,"price":0.18925999999999998,"pricemin":0.18925999999999998},{"year":"2022","month":"12","day":"26","hour":20,"price":0.15,"pricemin":0.15},{"year":"2022","month":"12","day":"26","hour":21,"price":0.13998,"pricemin":0.13998},{"year":"2022","month":"12","day":"26","hour":22,"price":0.15486000000000003,"pricemin":0.15486000000000003},{"year":"2022","month":"12","day":"26","hour":23,"price":0.13256,"pricemin":0.13256},{"year":"*\r","hour":null,"price":null,"pricemin":null}]