[{"year":"2024","month":"12","day":"22","hour":0,"price":0.1005,"pricemin":0.1005},{"year":"2024","month":"12","day":"22","hour":1,"price":0.085,"pricemin":0.085},{"year":"2024","month":"12","day":"22","hour":2,"price":0.07262,"pricemin":0.07262},{"year":"2024","month":"12","day":"22","hour":3,"price":0.06498999999999999,"pricemin":0.06498999999999999},{"year":"2024","month":"12","day":"22","hour":4,"price":0.05988,"pricemin":0.05988},{"year":"2024","month":"12","day":"22","hour":5,"price":0.0592,"pricemin":0.0592},{"year":"2024","month":"12","day":"22","hour":6,"price":0.05963,"pricemin":0.05963},{"year":"2024","month":"12","day":"22","hour":7,"price":0.06028,"pricemin":0.06028},{"year":"2024","month":"12","day":"22","hour":8,"price":0.0603,"pricemin":0.0603},{"year":"2024","month":"12","day":"22","hour":9,"price":0.05024,"pricemin":0.05024},{"year":"2024","month":"12","day":"22","hour":10,"price":0.02,"pricemin":0.02},{"year":"2024","month":"12","day":"22","hour":11,"price":0.01601,"pricemin":0.01601},{"year":"2024","month":"12","day":"22","hour":12,"price":0.018670000000000003,"pricemin":0.018670000000000003},{"year":"2024","month":"12","day":"22","hour":13,"price":0.015380000000000001,"pricemin":0.015380000000000001},{"year":"2024","month":"12","day":"22","hour":14,"price":0.010960000000000001,"pricemin":0.010960000000000001},{"year":"2024","month":"12","day":"22","hour":15,"price":0.005,"pricemin":0.005},{"year":"2024","month":"12","day":"22","hour":16,"price":0.018600000000000002,"pricemin":0.018600000000000002},{"year":"2024","month":"12","day":"22","hour":17,"price":0.055,"pricemin":0.055},{"year":"2024","month":"12","day":"22","hour":18,"price":0.07744,"pricemin":0.07744},{"year":"2024","month":"12","day":"22","hour":19,"price":0.07997,"pricemin":0.07997},{"year":"2024","month":"12","day":"22","hour":20,"price":0.08475,"pricemin":0.08475},{"year":"2024","month":"12","day":"22","hour":21,"price":0.08497,"pricemin":0.08497},{"year":"2024","month":"12","day":"22","hour":22,"price":0.0703,"pricemin":0.0703},{"year":"2024","month":"12","day":"22","hour":23,"price":0.06459999999999999,"pricemin":0.06459999999999999},{"year":"*\r","hour":null,"price":null,"pricemin":null}]