[{"year":"2023","month":"05","day":"10","hour":0,"price":0.095,"pricemin":0.095},{"year":"2023","month":"05","day":"10","hour":1,"price":0.09009,"pricemin":0.09009},{"year":"2023","month":"05","day":"10","hour":2,"price":0.08838,"pricemin":0.08838},{"year":"2023","month":"05","day":"10","hour":3,"price":0.08619,"pricemin":0.08619},{"year":"2023","month":"05","day":"10","hour":4,"price":0.08177,"pricemin":0.08177},{"year":"2023","month":"05","day":"10","hour":5,"price":0.08101,"pricemin":0.08101},{"year":"2023","month":"05","day":"10","hour":6,"price":0.0888,"pricemin":0.0888},{"year":"2023","month":"05","day":"10","hour":7,"price":0.10428,"pricemin":0.10428},{"year":"2023","month":"05","day":"10","hour":8,"price":0.105,"pricemin":0.105},{"year":"2023","month":"05","day":"10","hour":9,"price":0.084,"pricemin":0.084},{"year":"2023","month":"05","day":"10","hour":10,"price":0.07042,"pricemin":0.07042},{"year":"2023","month":"05","day":"10","hour":11,"price":0.06961,"pricemin":0.06961},{"year":"2023","month":"05","day":"10","hour":12,"price":0.06916,"pricemin":0.06916},{"year":"2023","month":"05","day":"10","hour":13,"price":0.06891,"pricemin":0.06891},{"year":"2023","month":"05","day":"10","hour":14,"price":0.06,"pricemin":0.06},{"year":"2023","month":"05","day":"10","hour":15,"price":0.04521,"pricemin":0.04521},{"year":"2023","month":"05","day":"10","hour":16,"price":0.0451,"pricemin":0.0451},{"year":"2023","month":"05","day":"10","hour":17,"price":0.049,"pricemin":0.049},{"year":"2023","month":"05","day":"10","hour":18,"price":0.068,"pricemin":0.068},{"year":"2023","month":"05","day":"10","hour":19,"price":0.07762000000000001,"pricemin":0.07762000000000001},{"year":"2023","month":"05","day":"10","hour":20,"price":0.10546,"pricemin":0.10546},{"year":"2023","month":"05","day":"10","hour":21,"price":0.129,"pricemin":0.129},{"year":"2023","month":"05","day":"10","hour":22,"price":0.11531999999999999,"pricemin":0.11531999999999999},{"year":"2023","month":"05","day":"10","hour":23,"price":0.10911,"pricemin":0.10911},{"year":"*\r","hour":null,"price":null,"pricemin":null}]