[{"year":"2023","month":"11","day":"11","hour":0,"price":0.01908,"pricemin":0.01908},{"year":"2023","month":"11","day":"11","hour":1,"price":0.00939,"pricemin":0.00939},{"year":"2023","month":"11","day":"11","hour":2,"price":0.00623,"pricemin":0.00623},{"year":"2023","month":"11","day":"11","hour":3,"price":0.0043,"pricemin":0.0043},{"year":"2023","month":"11","day":"11","hour":4,"price":0.0043,"pricemin":0.0043},{"year":"2023","month":"11","day":"11","hour":5,"price":0.005,"pricemin":0.005},{"year":"2023","month":"11","day":"11","hour":6,"price":0.00729,"pricemin":0.00729},{"year":"2023","month":"11","day":"11","hour":7,"price":0.00939,"pricemin":0.00939},{"year":"2023","month":"11","day":"11","hour":8,"price":0.01,"pricemin":0.01},{"year":"2023","month":"11","day":"11","hour":9,"price":0.01,"pricemin":0.01},{"year":"2023","month":"11","day":"11","hour":10,"price":0.00729,"pricemin":0.00729},{"year":"2023","month":"11","day":"11","hour":11,"price":0.0043,"pricemin":0.0043},{"year":"2023","month":"11","day":"11","hour":12,"price":0.0043,"pricemin":0.0043},{"year":"2023","month":"11","day":"11","hour":13,"price":0.0043,"pricemin":0.0043},{"year":"2023","month":"11","day":"11","hour":14,"price":0.0043,"pricemin":0.0043},{"year":"2023","month":"11","day":"11","hour":15,"price":0.0016200000000000001,"pricemin":0.0016200000000000001},{"year":"2023","month":"11","day":"11","hour":16,"price":0.0043,"pricemin":0.0043},{"year":"2023","month":"11","day":"11","hour":17,"price":0.0074199999999999995,"pricemin":0.0074199999999999995},{"year":"2023","month":"11","day":"11","hour":18,"price":0.011699999999999999,"pricemin":0.011699999999999999},{"year":"2023","month":"11","day":"11","hour":19,"price":0.01914,"pricemin":0.01914},{"year":"2023","month":"11","day":"11","hour":20,"price":0.02017,"pricemin":0.02017},{"year":"2023","month":"11","day":"11","hour":21,"price":0.01908,"pricemin":0.01908},{"year":"2023","month":"11","day":"11","hour":22,"price":0.01039,"pricemin":0.01039},{"year":"2023","month":"11","day":"11","hour":23,"price":0.0062900000000000005,"pricemin":0.0062900000000000005},{"year":"*\r","hour":null,"price":null,"pricemin":null}]