{"PVPC":[{"Dia":"01/03/2023","Hora":"00-01","PCB":"195,75","CYM":"195,75","COF2TD":"0,000105306132000000","PMHPCB":"177,05","PMHCYM":"177,05","SAHPCB":"11,41","SAHCYM":"11,41","FOMPCB":"0,05","FOMCYM":"0,05","FOSPCB":"0,19","FOSCYM":"0,19","INTPCB":"0,00","INTCYM":"0,00","PCAPPCB":"0,00","PCAPCYM":"0,00","TEUPCB":"3,18","TEUCYM":"3,18","CCVPCB":"3,89","CCVCYM":"3,89","EDSRPCB":"0,00","EDSRCYM":"0,00","EDCGASPCB":"0,00","EDCGASCYM":"0,00"},{"Dia":"01/03/2023","Hora":"01-02","PCB":"191,48","CYM":"191,48","COF2TD":"0,000086011484000000","PMHPCB":"172,08","PMHCYM":"172,08","SAHPCB":"12,16","SAHCYM":"12,16","FOMPCB":"0,05","FOMCYM":"0,05","FOSPCB":"0,20","FOSCYM":"0,20","INTPCB":"0,00","INTCYM":"0,00","PCAPPCB":"0,00","PCAPCYM":"0,00","TEUPCB":"3,18","TEUCYM":"3,18","CCVPCB":"3,83","CCVCYM":"3,83","EDSRPCB":"0,00","EDSRCYM":"0,00","EDCGASPCB":"0,00","EDCGASCYM":"0,00"},{"Dia":"01/03/2023","Hora":"02-03","PCB":"192,75","CYM":"192,75","COF2TD":"0,000075829387000000","PMHPCB":"172,90","PMHCYM":"172,90","SAHPCB":"12,58","SAHCYM":"12,58","FOMPCB":"0,05","FOMCYM":"0,05","FOSPCB":"0,20","FOSCYM":"0,20","INTPCB":"0,00","INTCYM":"0,00","PCAPPCB":"0,00","PCAPCYM":"0,00","TEUPCB":"3,18","TEUCYM":"3,18","CCVPCB":"3,85","CCVCYM":"3,85","EDSRPCB":"0,00","EDSRCYM":"0,00","EDCGASPCB":"0,00","EDCGASCYM":"0,00"},{"Dia":"01/03/2023","Hora":"03-04","PCB":"188,34","CYM":"188,34","COF2TD":"0,000071136542000000","PMHPCB":"167,69","PMHCYM":"167,69","SAHPCB":"13,45","SAHCYM":"13,45","FOMPCB":"0,05","FOMCYM":"0,05","FOSPCB":"0,20","FOSCYM":"0,20","INTPCB":"0,00","INTCYM":"0,00","PCAPPCB":"0,00","PCAPCYM":"0,00","TEUPCB":"3,18","TEUCYM":"3,18","CCVPCB":"3,79","CCVCYM":"3,79","EDSRPCB":"0,00","EDSRCYM":"0,00","EDCGASPCB":"0,00","EDCGASCYM":"0,00"},{"Dia":"01/03/2023","Hora":"04-05","PCB":"182,50","CYM":"182,50","COF2TD":"0,000069692320000000","PMHPCB":"161,72","PMHCYM":"161,72","SAHPCB":"13,67","SAHCYM":"13,67","FOMPCB":"0,05","FOMCYM":"0,05","FOSPCB":"0,20","FOSCYM":"0,20","INTPCB":"0,00","INTCYM":"0,00","PCAPPCB":"0,00","PCAPCYM":"0,00","TEUPCB":"3,18","TEUCYM":"3,18","CCVPCB":"3,70","CCVCYM":"3,70","EDSRPCB":"0,00","EDSRCYM":"0,00","EDCGASPCB":"0,00","EDCGASCYM":"0,00"},{"Dia":"01/03/2023","Hora":"05-06","PCB":"192,25","CYM":"192,25","COF2TD":"0,000072350897000000","PMHPCB":"172,27","PMHCYM":"172,27","SAHPCB":"12,72","SAHCYM":"12,72","FOMPCB":"0,05","FOMCYM":"0,05","FOSPCB":"0,20","FOSCYM":"0,20","INTPCB":"0,00","INTCYM":"0,00","PCAPPCB":"0,00","PCAPCYM":"0,00","TEUPCB":"3,18","TEUCYM":"3,18","CCVPCB":"3,84","CCVCYM":"3,84","EDSRPCB":"0,00","EDSRCYM":"0,00","EDCGASPCB":"0,00","EDCGASCYM":"0,00"},{"Dia":"01/03/2023","Hora":"06-07","PCB":"206,20","CYM":"206,20","COF2TD":"0,000083550323000000","PMHPCB":"188,33","PMHCYM":"188,33","SAHPCB":"10,42","SAHCYM":"10,42","FOMPCB":"0,04","FOMCYM":"0,04","FOSPCB":"0,19","FOSCYM":"0,19","INTPCB":"0,00","INTCYM":"0,00","PCAPPCB":"0,00","PCAPCYM":"0,00","TEUPCB":"3,18","TEUCYM":"3,18","CCVPCB":"4,04","CCVCYM":"4,04","EDSRPCB":"0,00","EDSRCYM":"0,00","EDCGASPCB":"0,00","EDCGASCYM":"0,00"},{"Dia":"01/03/2023","Hora":"07-08","PCB":"209,27","CYM":"209,27","COF2TD":"0,000105283558000000","PMHPCB":"192,44","PMHCYM":"192,44","SAHPCB":"9,35","SAHCYM":"9,35","FOMPCB":"0,04","FOMCYM":"0,04","FOSPCB":"0,19","FOSCYM":"0,19","INTPCB":"0,00","INTCYM":"0,00","PCAPPCB":"0,00","PCAPCYM":"0,00","TEUPCB":"3,18","TEUCYM":"3,18","CCVPCB":"4,07","CCVCYM":"4,07","EDSRPCB":"0,00","EDSRCYM":"0,00","EDCGASPCB":"0,00","EDCGASCYM":"0,00"},{"Dia":"01/03/2023","Hora":"08-09","PCB":"236,78","CYM":"236,78","COF2TD":"0,000117805092000000","PMHPCB":"195,65","PMHCYM":"195,65","SAHPCB":"8,02","SAHCYM":"8,02","FOMPCB":"0,04","FOMCYM":"0,04","FOSPCB":"0,19","FOSCYM":"0,19","INTPCB":"0,00","INTCYM":"0,00","PCAPPCB":"0,21","PCAPCYM":"0,21","TEUPCB":"28,57","TEUCYM":"28,57","CCVPCB":"4,09","CCVCYM":"4,09","EDSRPCB":"0,00","EDSRCYM":"0,00","EDCGASPCB":"0,00","EDCGASCYM":"0,00"},{"Dia":"01/03/2023","Hora":"09-10","PCB":"228,62","CYM":"228,62","COF2TD":"0,000123375691000000","PMHPCB":"187,34","PMHCYM":"187,34","SAHPCB":"8,31","SAHCYM":"8,31","FOMPCB":"0,04","FOMCYM":"0,04","FOSPCB":"0,19","FOSCYM":"0,19","INTPCB":"0,00","INTCYM":"0,00","PCAPPCB":"0,21","PCAPCYM":"0,21","TEUPCB":"28,57","TEUCYM":"28,57","CCVPCB":"3,96","CCVCYM":"3,96","EDSRPCB":"0,00","EDSRCYM":"0,00","EDCGASPCB":"0,00","EDCGASCYM":"0,00"},{"Dia":"01/03/2023","Hora":"10-11","PCB":"259,34","CYM":"213,23","COF2TD":"0,000128301951000000","PMHPCB":"171,81","PMHCYM":"171,23","SAHPCB":"9,30","SAHCYM":"9,27","FOMPCB":"0,04","FOMCYM":"0,04","FOSPCB":"0,19","FOSCYM":"0,19","INTPCB":"0,00","INTCYM":"0,00","PCAPPCB":"1,25","PCAPCYM":"0,21","TEUPCB":"72,99","TEUCYM":"28,57","CCVPCB":"3,75","CCVCYM":"3,72","EDSRPCB":"0,00","EDSRCYM":"0,00","EDCGASPCB":"0,00","EDCGASCYM":"0,00"},{"Dia":"01/03/2023","Hora":"11-12","PCB":"247,75","CYM":"247,75","COF2TD":"0,000128085024000000","PMHPCB":"159,59","PMHCYM":"159,59","SAHPCB":"10,10","SAHCYM":"10,10","FOMPCB":"0,04","FOMCYM":"0,04","FOSPCB":"0,19","FOSCYM":"0,19","INTPCB":"0,00","INTCYM":"0,00","PCAPPCB":"1,25","PCAPCYM":"1,25","TEUPCB":"72,99","TEUCYM":"72,99","CCVPCB":"3,58","CCVCYM":"3,58","EDSRPCB":"0,00","EDSRCYM":"0,00","EDCGASPCB":"0,00","EDCGASCYM":"0,00"},{"Dia":"01/03/2023","Hora":"12-13","PCB":"242,36","CYM":"242,36","COF2TD":"0,000128843095000000","PMHPCB":"154,97","PMHCYM":"154,97","SAHPCB":"9,42","SAHCYM":"9,42","FOMPCB":"0,04","FOMCYM":"0,04","FOSPCB":"0,19","FOSCYM":"0,19","INTPCB":"0,00","INTCYM":"0,00","PCAPPCB":"1,25","PCAPCYM":"1,25","TEUPCB":"72,99","TEUCYM":"72,99","CCVPCB":"3,50","CCVCYM":"3,50","EDSRPCB":"0,00","EDSRCYM":"0,00","EDCGASPCB":"0,00","EDCGASCYM":"0,00"},{"Dia":"01/03/2023","Hora":"13-14","PCB":"240,59","CYM":"240,59","COF2TD":"0,000135604445000000","PMHPCB":"152,94","PMHCYM":"152,94","SAHPCB":"9,71","SAHCYM":"9,71","FOMPCB":"0,04","FOMCYM":"0,04","FOSPCB":"0,19","FOSCYM":"0,19","INTPCB":"0,00","INTCYM":"0,00","PCAPPCB":"1,25","PCAPCYM":"1,25","TEUPCB":"72,99","TEUCYM":"72,99","CCVPCB":"3,47","CCVCYM":"3,47","EDSRPCB":"0,00","EDSRCYM":"0,00","EDCGASPCB":"0,00","EDCGASCYM":"0,00"},{"Dia":"01/03/2023","Hora":"14-15","PCB":"189,90","CYM":"235,93","COF2TD":"0,000135088761000000","PMHPCB":"147,83","PMHCYM":"148,34","SAHPCB":"9,67","SAHCYM":"9,70","FOMPCB":"0,04","FOMCYM":"0,04","FOSPCB":"0,19","FOSCYM":"0,19","INTPCB":"0,00","INTCYM":"0,00","PCAPPCB":"0,21","PCAPCYM":"1,26","TEUPCB":"28,57","TEUCYM":"72,99","CCVPCB":"3,38","CCVCYM":"3,41","EDSRPCB":"0,00","EDSRCYM":"0,00","EDCGASPCB":"0,00","EDCGASCYM":"0,00"},{"Dia":"01/03/2023","Hora":"15-16","PCB":"185,68","CYM":"185,68","COF2TD":"0,000126899149000000","PMHPCB":"143,65","PMHCYM":"143,65","SAHPCB":"9,69","SAHCYM":"9,69","FOMPCB":"0,04","FOMCYM":"0,04","FOSPCB":"0,19","FOSCYM":"0,19","INTPCB":"0,00","INTCYM":"0,00","PCAPPCB":"0,21","PCAPCYM":"0,21","TEUPCB":"28,57","TEUCYM":"28,57","CCVPCB":"3,33","CCVCYM":"3,33","EDSRPCB":"0,00","EDSRCYM":"0,00","EDCGASPCB":"0,00","EDCGASCYM":"0,00"},{"Dia":"01/03/2023","Hora":"16-17","PCB":"192,89","CYM":"192,89","COF2TD":"0,000120580370000000","PMHPCB":"150,01","PMHCYM":"150,01","SAHPCB":"10,42","SAHCYM":"10,42","FOMPCB":"0,04","FOMCYM":"0,04","FOSPCB":"0,19","FOSCYM":"0,19","INTPCB":"0,00","INTCYM":"0,00","PCAPPCB":"0,21","PCAPCYM":"0,21","TEUPCB":"28,57","TEUCYM":"28,57","CCVPCB":"3,44","CCVCYM":"3,44","EDSRPCB":"0,00","EDSRCYM":"0,00","EDCGASPCB":"0,00","EDCGASCYM":"0,00"},{"Dia":"01/03/2023","Hora":"17-18","PCB":"217,96","CYM":"217,96","COF2TD":"0,000120514980000000","PMHPCB":"175,52","PMHCYM":"175,52","SAHPCB":"9,61","SAHCYM":"9,61","FOMPCB":"0,04","FOMCYM":"0,04","FOSPCB":"0,19","FOSCYM":"0,19","INTPCB":"0,00","INTCYM":"0,00","PCAPPCB":"0,21","PCAPCYM":"0,21","TEUPCB":"28,57","TEUCYM":"28,57","CCVPCB":"3,81","CCVCYM":"3,81","EDSRPCB":"0,00","EDSRCYM":"0,00","EDCGASPCB":"0,00","EDCGASCYM":"0,00"},{"Dia":"01/03/2023","Hora":"18-19","PCB":"268,29","CYM":"221,98","COF2TD":"0,000127079424000000","PMHPCB":"179,98","PMHCYM":"179,22","SAHPCB":"9,91","SAHCYM":"9,87","FOMPCB":"0,04","FOMCYM":"0,04","FOSPCB":"0,19","FOSCYM":"0,19","INTPCB":"0,00","INTCYM":"0,00","PCAPPCB":"1,27","PCAPCYM":"0,21","TEUPCB":"72,99","TEUCYM":"28,57","CCVPCB":"3,90","CCVCYM":"3,87","EDSRPCB":"0,00","EDSRCYM":"0,00","EDCGASPCB":"0,00","EDCGASCYM":"0,00"},{"Dia":"01/03/2023","Hora":"19-20","PCB":"286,84","CYM":"286,84","COF2TD":"0,000152880218000000","PMHPCB":"199,08","PMHCYM":"199,08","SAHPCB":"9,08","SAHCYM":"9,08","FOMPCB":"0,04","FOMCYM":"0,04","FOSPCB":"0,19","FOSCYM":"0,19","INTPCB":"0,00","INTCYM":"0,00","PCAPPCB":"1,27","PCAPCYM":"1,27","TEUPCB":"72,99","TEUCYM":"72,99","CCVPCB":"4,18","CCVCYM":"4,18","EDSRPCB":"0,00","EDSRCYM":"0,00","EDCGASPCB":"0,00","EDCGASCYM":"0,00"},{"Dia":"01/03/2023","Hora":"20-21","PCB":"290,86","CYM":"290,86","COF2TD":"0,000175953839000000","PMHPCB":"203,47","PMHCYM":"203,47","SAHPCB":"8,64","SAHCYM":"8,64","FOMPCB":"0,04","FOMCYM":"0,04","FOSPCB":"0,19","FOSCYM":"0,19","INTPCB":"0,00","INTCYM":"0,00","PCAPPCB":"1,28","PCAPCYM":"1,28","TEUPCB":"72,99","TEUCYM":"72,99","CCVPCB":"4,24","CCVCYM":"4,24","EDSRPCB":"0,00","EDSRCYM":"0,00","EDCGASPCB":"0,00","EDCGASCYM":"0,00"},{"Dia":"01/03/2023","Hora":"21-22","PCB":"283,24","CYM":"283,24","COF2TD":"0,000179173267000000","PMHPCB":"195,79","PMHCYM":"195,79","SAHPCB":"8,81","SAHCYM":"8,81","FOMPCB":"0,04","FOMCYM":"0,04","FOSPCB":"0,19","FOSCYM":"0,19","INTPCB":"0,00","INTCYM":"0,00","PCAPPCB":"1,28","PCAPCYM":"1,28","TEUPCB":"72,99","TEUCYM":"72,99","CCVPCB":"4,13","CCVCYM":"4,13","EDSRPCB":"0,00","EDSRCYM":"0,00","EDCGASPCB":"0,00","EDCGASCYM":"0,00"},{"Dia":"01/03/2023","Hora":"22-23","PCB":"235,32","CYM":"281,69","COF2TD":"0,000161244762000000","PMHPCB":"193,38","PMHCYM":"194,18","SAHPCB":"8,82","SAHCYM":"8,86","FOMPCB":"0,04","FOMCYM":"0,04","FOSPCB":"0,19","FOSCYM":"0,19","INTPCB":"0,00","INTCYM":"0,00","PCAPPCB":"0,22","PCAPCYM":"1,30","TEUPCB":"28,57","TEUCYM":"72,99","CCVPCB":"4,09","CCVCYM":"4,12","EDSRPCB":"0,00","EDSRCYM":"0,00","EDCGASPCB":"0,00","EDCGASCYM":"0,00"},{"Dia":"01/03/2023","Hora":"23-24","PCB":"227,77","CYM":"227,77","COF2TD":"0,000133725001000000","PMHPCB":"184,78","PMHCYM":"184,78","SAHPCB":"9,98","SAHCYM":"9,98","FOMPCB":"0,05","FOMCYM":"0,05","FOSPCB":"0,19","FOSCYM":"0,19","INTPCB":"0,00","INTCYM":"0,00","PCAPPCB":"0,22","PCAPCYM":"0,22","TEUPCB":"28,57","TEUCYM":"28,57","CCVPCB":"3,98","CCVCYM":"3,98","EDSRPCB":"0,00","EDSRCYM":"0,00","EDCGASPCB":"0,00","EDCGASCYM":"0,00"}]}