{"PVPC":[{"Dia":"27/02/2023","Hora":"00-01","PCB":"149,24","CYM":"149,24","COF2TD":"0,000106638873000000","PMHPCB":"123,06","PMHCYM":"123,06","SAHPCB":"19,56","SAHCYM":"19,56","FOMPCB":"0,05","FOMCYM":"0,05","FOSPCB":"0,20","FOSCYM":"0,20","INTPCB":"0,00","INTCYM":"0,00","PCAPPCB":"0,00","PCAPCYM":"0,00","TEUPCB":"3,18","TEUCYM":"3,18","CCVPCB":"3,20","CCVCYM":"3,20","EDSRPCB":"0,00","EDSRCYM":"0,00","EDCGASPCB":"0,00","EDCGASCYM":"0,00"},{"Dia":"27/02/2023","Hora":"01-02","PCB":"151,26","CYM":"151,26","COF2TD":"0,000087631538000000","PMHPCB":"121,59","PMHCYM":"121,59","SAHPCB":"23,01","SAHCYM":"23,01","FOMPCB":"0,05","FOMCYM":"0,05","FOSPCB":"0,20","FOSCYM":"0,20","INTPCB":"0,00","INTCYM":"0,00","PCAPPCB":"0,00","PCAPCYM":"0,00","TEUPCB":"3,18","TEUCYM":"3,18","CCVPCB":"3,24","CCVCYM":"3,24","EDSRPCB":"0,00","EDSRCYM":"0,00","EDCGASPCB":"0,00","EDCGASCYM":"0,00"},{"Dia":"27/02/2023","Hora":"02-03","PCB":"143,92","CYM":"143,92","COF2TD":"0,000077206486000000","PMHPCB":"113,31","PMHCYM":"113,31","SAHPCB":"24,05","SAHCYM":"24,05","FOMPCB":"0,05","FOMCYM":"0,05","FOSPCB":"0,20","FOSCYM":"0,20","INTPCB":"0,00","INTCYM":"0,00","PCAPPCB":"0,00","PCAPCYM":"0,00","TEUPCB":"3,18","TEUCYM":"3,18","CCVPCB":"3,13","CCVCYM":"3,13","EDSRPCB":"0,00","EDSRCYM":"0,00","EDCGASPCB":"0,00","EDCGASCYM":"0,00"},{"Dia":"27/02/2023","Hora":"03-04","PCB":"144,68","CYM":"144,68","COF2TD":"0,000072191877000000","PMHPCB":"112,65","PMHCYM":"112,65","SAHPCB":"25,46","SAHCYM":"25,46","FOMPCB":"0,05","FOMCYM":"0,05","FOSPCB":"0,20","FOSCYM":"0,20","INTPCB":"0,00","INTCYM":"0,00","PCAPPCB":"0,00","PCAPCYM":"0,00","TEUPCB":"3,18","TEUCYM":"3,18","CCVPCB":"3,14","CCVCYM":"3,14","EDSRPCB":"0,00","EDSRCYM":"0,00","EDCGASPCB":"0,00","EDCGASCYM":"0,00"},{"Dia":"27/02/2023","Hora":"04-05","PCB":"144,82","CYM":"144,82","COF2TD":"0,000070597390000000","PMHPCB":"112,61","PMHCYM":"112,61","SAHPCB":"25,65","SAHCYM":"25,65","FOMPCB":"0,05","FOMCYM":"0,05","FOSPCB":"0,20","FOSCYM":"0,20","INTPCB":"0,00","INTCYM":"0,00","PCAPPCB":"0,00","PCAPCYM":"0,00","TEUPCB":"3,18","TEUCYM":"3,18","CCVPCB":"3,14","CCVCYM":"3,14","EDSRPCB":"0,00","EDSRCYM":"0,00","EDCGASPCB":"0,00","EDCGASCYM":"0,00"},{"Dia":"27/02/2023","Hora":"05-06","PCB":"152,24","CYM":"152,24","COF2TD":"0,000073302035000000","PMHPCB":"121,46","PMHCYM":"121,46","SAHPCB":"24,11","SAHCYM":"24,11","FOMPCB":"0,05","FOMCYM":"0,05","FOSPCB":"0,20","FOSCYM":"0,20","INTPCB":"0,00","INTCYM":"0,00","PCAPPCB":"0,00","PCAPCYM":"0,00","TEUPCB":"3,18","TEUCYM":"3,18","CCVPCB":"3,25","CCVCYM":"3,25","EDSRPCB":"0,00","EDSRCYM":"0,00","EDCGASPCB":"0,00","EDCGASCYM":"0,00"},{"Dia":"27/02/2023","Hora":"06-07","PCB":"155,73","CYM":"155,73","COF2TD":"0,000084605541000000","PMHPCB":"128,96","PMHCYM":"128,96","SAHPCB":"20,08","SAHCYM":"20,08","FOMPCB":"0,04","FOMCYM":"0,04","FOSPCB":"0,19","FOSCYM":"0,19","INTPCB":"0,00","INTCYM":"0,00","PCAPPCB":"0,00","PCAPCYM":"0,00","TEUPCB":"3,18","TEUCYM":"3,18","CCVPCB":"3,28","CCVCYM":"3,28","EDSRPCB":"0,00","EDSRCYM":"0,00","EDCGASPCB":"0,00","EDCGASCYM":"0,00"},{"Dia":"27/02/2023","Hora":"07-08","PCB":"192,89","CYM":"192,89","COF2TD":"0,000107186633000000","PMHPCB":"172,13","PMHCYM":"172,13","SAHPCB":"13,53","SAHCYM":"13,53","FOMPCB":"0,04","FOMCYM":"0,04","FOSPCB":"0,19","FOSCYM":"0,19","INTPCB":"0,00","INTCYM":"0,00","PCAPPCB":"0,00","PCAPCYM":"0,00","TEUPCB":"3,18","TEUCYM":"3,18","CCVPCB":"3,82","CCVCYM":"3,82","EDSRPCB":"0,00","EDSRCYM":"0,00","EDCGASPCB":"0,00","EDCGASCYM":"0,00"},{"Dia":"27/02/2023","Hora":"08-09","PCB":"218,51","CYM":"218,51","COF2TD":"0,000118043156000000","PMHPCB":"175,01","PMHCYM":"175,01","SAHPCB":"10,68","SAHCYM":"10,68","FOMPCB":"0,04","FOMCYM":"0,04","FOSPCB":"0,19","FOSCYM":"0,19","INTPCB":"0,00","INTCYM":"0,00","PCAPPCB":"0,21","PCAPCYM":"0,21","TEUPCB":"28,57","TEUCYM":"28,57","CCVPCB":"3,81","CCVCYM":"3,81","EDSRPCB":"0,00","EDSRCYM":"0,00","EDCGASPCB":"0,00","EDCGASCYM":"0,00"},{"Dia":"27/02/2023","Hora":"09-10","PCB":"194,45","CYM":"194,45","COF2TD":"0,000124180819000000","PMHPCB":"147,46","PMHCYM":"147,46","SAHPCB":"14,54","SAHCYM":"14,54","FOMPCB":"0,04","FOMCYM":"0,04","FOSPCB":"0,19","FOSCYM":"0,19","INTPCB":"0,00","INTCYM":"0,00","PCAPPCB":"0,21","PCAPCYM":"0,21","TEUPCB":"28,57","TEUCYM":"28,57","CCVPCB":"3,44","CCVCYM":"3,44","EDSRPCB":"0,00","EDSRCYM":"0,00","EDCGASPCB":"0,00","EDCGASCYM":"0,00"},{"Dia":"27/02/2023","Hora":"10-11","PCB":"210,19","CYM":"164,25","COF2TD":"0,000130597831000000","PMHPCB":"116,75","PMHCYM":"116,35","SAHPCB":"15,96","SAHCYM":"15,91","FOMPCB":"0,04","FOMCYM":"0,04","FOSPCB":"0,19","FOSCYM":"0,19","INTPCB":"0,00","INTCYM":"0,00","PCAPPCB":"1,25","PCAPCYM":"0,21","TEUPCB":"72,99","TEUCYM":"28,57","CCVPCB":"3,01","CCVCYM":"2,99","EDSRPCB":"0,00","EDSRCYM":"0,00","EDCGASPCB":"0,00","EDCGASCYM":"0,00"},{"Dia":"27/02/2023","Hora":"11-12","PCB":"207,56","CYM":"207,56","COF2TD":"0,000129933946000000","PMHPCB":"113,89","PMHCYM":"113,89","SAHPCB":"16,22","SAHCYM":"16,22","FOMPCB":"0,04","FOMCYM":"0,04","FOSPCB":"0,19","FOSCYM":"0,19","INTPCB":"0,00","INTCYM":"0,00","PCAPPCB":"1,25","PCAPCYM":"1,25","TEUPCB":"72,99","TEUCYM":"72,99","CCVPCB":"2,97","CCVCYM":"2,97","EDSRPCB":"0,00","EDSRCYM":"0,00","EDCGASPCB":"0,00","EDCGASCYM":"0,00"},{"Dia":"27/02/2023","Hora":"12-13","PCB":"207,11","CYM":"207,11","COF2TD":"0,000129578339000000","PMHPCB":"114,01","PMHCYM":"114,01","SAHPCB":"15,66","SAHCYM":"15,66","FOMPCB":"0,04","FOMCYM":"0,04","FOSPCB":"0,19","FOSCYM":"0,19","INTPCB":"0,00","INTCYM":"0,00","PCAPPCB":"1,25","PCAPCYM":"1,25","TEUPCB":"72,99","TEUCYM":"72,99","CCVPCB":"2,97","CCVCYM":"2,97","EDSRPCB":"0,00","EDSRCYM":"0,00","EDCGASPCB":"0,00","EDCGASCYM":"0,00"},{"Dia":"27/02/2023","Hora":"13-14","PCB":"206,96","CYM":"206,96","COF2TD":"0,000135591709000000","PMHPCB":"113,82","PMHCYM":"113,82","SAHPCB":"15,71","SAHCYM":"15,71","FOMPCB":"0,04","FOMCYM":"0,04","FOSPCB":"0,19","FOSCYM":"0,19","INTPCB":"0,00","INTCYM":"0,00","PCAPPCB":"1,25","PCAPCYM":"1,25","TEUPCB":"72,99","TEUCYM":"72,99","CCVPCB":"2,96","CCVCYM":"2,96","EDSRPCB":"0,00","EDSRCYM":"0,00","EDCGASPCB":"0,00","EDCGASCYM":"0,00"},{"Dia":"27/02/2023","Hora":"14-15","PCB":"152,87","CYM":"198,77","COF2TD":"0,000135098990000000","PMHPCB":"105,28","PMHCYM":"105,64","SAHPCB":"15,76","SAHCYM":"15,82","FOMPCB":"0,04","FOMCYM":"0,04","FOSPCB":"0,19","FOSCYM":"0,19","INTPCB":"0,00","INTCYM":"0,00","PCAPPCB":"0,21","PCAPCYM":"1,25","TEUPCB":"28,57","TEUCYM":"72,99","CCVPCB":"2,82","CCVCYM":"2,84","EDSRPCB":"0,00","EDSRCYM":"0,00","EDCGASPCB":"0,00","EDCGASCYM":"0,00"},{"Dia":"27/02/2023","Hora":"15-16","PCB":"162,22","CYM":"162,22","COF2TD":"0,000126912112000000","PMHPCB":"114,31","PMHCYM":"114,31","SAHPCB":"15,94","SAHCYM":"15,94","FOMPCB":"0,04","FOMCYM":"0,04","FOSPCB":"0,19","FOSCYM":"0,19","INTPCB":"0,00","INTCYM":"0,00","PCAPPCB":"0,21","PCAPCYM":"0,21","TEUPCB":"28,57","TEUCYM":"28,57","CCVPCB":"2,96","CCVCYM":"2,96","EDSRPCB":"0,00","EDSRCYM":"0,00","EDCGASPCB":"0,00","EDCGASCYM":"0,00"},{"Dia":"27/02/2023","Hora":"16-17","PCB":"165,82","CYM":"165,82","COF2TD":"0,000120407447000000","PMHPCB":"117,09","PMHCYM":"117,09","SAHPCB":"16,69","SAHCYM":"16,69","FOMPCB":"0,04","FOMCYM":"0,04","FOSPCB":"0,19","FOSCYM":"0,19","INTPCB":"0,00","INTCYM":"0,00","PCAPPCB":"0,21","PCAPCYM":"0,21","TEUPCB":"28,57","TEUCYM":"28,57","CCVPCB":"3,02","CCVCYM":"3,02","EDSRPCB":"0,00","EDSRCYM":"0,00","EDCGASPCB":"0,00","EDCGASCYM":"0,00"},{"Dia":"27/02/2023","Hora":"17-18","PCB":"173,26","CYM":"173,26","COF2TD":"0,000120999980000000","PMHPCB":"125,97","PMHCYM":"125,97","SAHPCB":"15,14","SAHCYM":"15,14","FOMPCB":"0,04","FOMCYM":"0,04","FOSPCB":"0,19","FOSCYM":"0,19","INTPCB":"0,00","INTCYM":"0,00","PCAPPCB":"0,21","PCAPCYM":"0,21","TEUPCB":"28,57","TEUCYM":"28,57","CCVPCB":"3,13","CCVCYM":"3,13","EDSRPCB":"0,00","EDSRCYM":"0,00","EDCGASPCB":"0,00","EDCGASCYM":"0,00"},{"Dia":"27/02/2023","Hora":"18-19","PCB":"261,01","CYM":"214,89","COF2TD":"0,000131372625000000","PMHPCB":"170,67","PMHCYM":"170,09","SAHPCB":"12,07","SAHCYM":"12,03","FOMPCB":"0,04","FOMCYM":"0,04","FOSPCB":"0,19","FOSCYM":"0,19","INTPCB":"0,00","INTCYM":"0,00","PCAPPCB":"1,26","PCAPCYM":"0,21","TEUPCB":"72,99","TEUCYM":"28,57","CCVPCB":"3,78","CCVCYM":"3,76","EDSRPCB":"0,00","EDSRCYM":"0,00","EDCGASPCB":"0,00","EDCGASCYM":"0,00"},{"Dia":"27/02/2023","Hora":"19-20","PCB":"283,32","CYM":"283,32","COF2TD":"0,000160922083000000","PMHPCB":"193,37","PMHCYM":"193,37","SAHPCB":"11,35","SAHCYM":"11,35","FOMPCB":"0,04","FOMCYM":"0,04","FOSPCB":"0,19","FOSCYM":"0,19","INTPCB":"0,00","INTCYM":"0,00","PCAPPCB":"1,26","PCAPCYM":"1,26","TEUPCB":"72,99","TEUCYM":"72,99","CCVPCB":"4,12","CCVCYM":"4,12","EDSRPCB":"0,00","EDSRCYM":"0,00","EDCGASPCB":"0,00","EDCGASCYM":"0,00"},{"Dia":"27/02/2023","Hora":"20-21","PCB":"298,66","CYM":"298,66","COF2TD":"0,000180774193000000","PMHPCB":"206,76","PMHCYM":"206,76","SAHPCB":"13,05","SAHCYM":"13,05","FOMPCB":"0,04","FOMCYM":"0,04","FOSPCB":"0,19","FOSCYM":"0,19","INTPCB":"0,00","INTCYM":"0,00","PCAPPCB":"1,27","PCAPCYM":"1,27","TEUPCB":"72,99","TEUCYM":"72,99","CCVPCB":"4,35","CCVCYM":"4,35","EDSRPCB":"0,00","EDSRCYM":"0,00","EDCGASPCB":"0,00","EDCGASCYM":"0,00"},{"Dia":"27/02/2023","Hora":"21-22","PCB":"282,69","CYM":"282,69","COF2TD":"0,000182309556000000","PMHPCB":"191,24","PMHCYM":"191,24","SAHPCB":"12,84","SAHCYM":"12,84","FOMPCB":"0,04","FOMCYM":"0,04","FOSPCB":"0,19","FOSCYM":"0,19","INTPCB":"0,00","INTCYM":"0,00","PCAPPCB":"1,27","PCAPCYM":"1,27","TEUPCB":"72,99","TEUCYM":"72,99","CCVPCB":"4,12","CCVCYM":"4,12","EDSRPCB":"0,00","EDSRCYM":"0,00","EDCGASPCB":"0,00","EDCGASCYM":"0,00"},{"Dia":"27/02/2023","Hora":"22-23","PCB":"230,31","CYM":"276,66","COF2TD":"0,000165241145000000","PMHPCB":"183,97","PMHCYM":"184,74","SAHPCB":"13,31","SAHCYM":"13,36","FOMPCB":"0,04","FOMCYM":"0,04","FOSPCB":"0,19","FOSCYM":"0,19","INTPCB":"0,00","INTCYM":"0,00","PCAPPCB":"0,21","PCAPCYM":"1,29","TEUPCB":"28,57","TEUCYM":"72,99","CCVPCB":"4,01","CCVCYM":"4,04","EDSRPCB":"0,00","EDSRCYM":"0,00","EDCGASPCB":"0,00","EDCGASCYM":"0,00"},{"Dia":"27/02/2023","Hora":"23-24","PCB":"218,10","CYM":"218,10","COF2TD":"0,000137011964000000","PMHPCB":"173,69","PMHCYM":"173,69","SAHPCB":"11,56","SAHCYM":"11,56","FOMPCB":"0,04","FOMCYM":"0,04","FOSPCB":"0,19","FOSCYM":"0,19","INTPCB":"0,00","INTCYM":"0,00","PCAPPCB":"0,21","PCAPCYM":"0,21","TEUPCB":"28,57","TEUCYM":"28,57","CCVPCB":"3,83","CCVCYM":"3,83","EDSRPCB":"0,00","EDSRCYM":"0,00","EDCGASPCB":"0,00","EDCGASCYM":"0,00"}]}