{"PVPC":[{"Dia":"05/04/2025","Hora":"00-01","PCB":"86,43","CYM":"86,43","COF2TD":"0,000105756145000000","PMHPCB":"40,63","PMHCYM":"40,63","SAHPCB":"21,74","SAHCYM":"21,74","FOMPCB":"0,05","FOMCYM":"0,05","FOSPCB":"0,20","FOSCYM":"0,20","INTPCB":"0,00","INTCYM":"0,00","PCAPPCB":"0,00","PCAPCYM":"0,00","TEUPCB":"2,99","TEUCYM":"2,99","CCVPCB":"3,74","CCVCYM":"3,74","EDSRPCB":"0,00","EDSRCYM":"0,00","TAHPCB":"17,08","TAHCYM":"17,08"},{"Dia":"05/04/2025","Hora":"01-02","PCB":"73,72","CYM":"73,72","COF2TD":"0,000089472118000000","PMHPCB":"24,01","PMHCYM":"24,01","SAHPCB":"25,73","SAHCYM":"25,73","FOMPCB":"0,05","FOMCYM":"0,05","FOSPCB":"0,20","FOSCYM":"0,20","INTPCB":"0,00","INTCYM":"0,00","PCAPPCB":"0,00","PCAPCYM":"0,00","TEUPCB":"2,99","TEUCYM":"2,99","CCVPCB":"3,56","CCVCYM":"3,56","EDSRPCB":"0,00","EDSRCYM":"0,00","TAHPCB":"17,17","TAHCYM":"17,17"},{"Dia":"05/04/2025","Hora":"02-03","PCB":"72,84","CYM":"72,84","COF2TD":"0,000078323135000000","PMHPCB":"22,29","PMHCYM":"22,29","SAHPCB":"26,49","SAHCYM":"26,49","FOMPCB":"0,05","FOMCYM":"0,05","FOSPCB":"0,20","FOSCYM":"0,20","INTPCB":"0,00","INTCYM":"0,00","PCAPPCB":"0,00","PCAPCYM":"0,00","TEUPCB":"2,99","TEUCYM":"2,99","CCVPCB":"3,56","CCVCYM":"3,56","EDSRPCB":"0,00","EDSRCYM":"0,00","TAHPCB":"17,25","TAHCYM":"17,25"},{"Dia":"05/04/2025","Hora":"03-04","PCB":"71,20","CYM":"71,20","COF2TD":"0,000071920948000000","PMHPCB":"22,52","PMHCYM":"22,52","SAHPCB":"24,67","SAHCYM":"24,67","FOMPCB":"0,05","FOMCYM":"0,05","FOSPCB":"0,20","FOSCYM":"0,20","INTPCB":"0,00","INTCYM":"0,00","PCAPPCB":"0,00","PCAPCYM":"0,00","TEUPCB":"2,99","TEUCYM":"2,99","CCVPCB":"3,53","CCVCYM":"3,53","EDSRPCB":"0,00","EDSRCYM":"0,00","TAHPCB":"17,24","TAHCYM":"17,24"},{"Dia":"05/04/2025","Hora":"04-05","PCB":"66,95","CYM":"66,95","COF2TD":"0,000069183790000000","PMHPCB":"15,79","PMHCYM":"15,79","SAHPCB":"27,19","SAHCYM":"27,19","FOMPCB":"0,05","FOMCYM":"0,05","FOSPCB":"0,20","FOSCYM":"0,20","INTPCB":"0,00","INTCYM":"0,00","PCAPPCB":"0,00","PCAPCYM":"0,00","TEUPCB":"2,99","TEUCYM":"2,99","CCVPCB":"3,47","CCVCYM":"3,47","EDSRPCB":"0,00","EDSRCYM":"0,00","TAHPCB":"17,25","TAHCYM":"17,25"},{"Dia":"05/04/2025","Hora":"05-06","PCB":"70,50","CYM":"70,50","COF2TD":"0,000069165892000000","PMHPCB":"19,52","PMHCYM":"19,52","SAHPCB":"26,95","SAHCYM":"26,95","FOMPCB":"0,05","FOMCYM":"0,05","FOSPCB":"0,20","FOSCYM":"0,20","INTPCB":"0,00","INTCYM":"0,00","PCAPPCB":"0,00","PCAPCYM":"0,00","TEUPCB":"2,99","TEUCYM":"2,99","CCVPCB":"3,53","CCVCYM":"3,53","EDSRPCB":"0,00","EDSRCYM":"0,00","TAHPCB":"17,27","TAHCYM":"17,27"},{"Dia":"05/04/2025","Hora":"06-07","PCB":"75,16","CYM":"75,16","COF2TD":"0,000071423391000000","PMHPCB":"23,89","PMHCYM":"23,89","SAHPCB":"27,18","SAHCYM":"27,18","FOMPCB":"0,05","FOMCYM":"0,05","FOSPCB":"0,20","FOSCYM":"0,20","INTPCB":"0,00","INTCYM":"0,00","PCAPPCB":"0,00","PCAPCYM":"0,00","TEUPCB":"2,99","TEUCYM":"2,99","CCVPCB":"3,59","CCVCYM":"3,59","EDSRPCB":"0,00","EDSRCYM":"0,00","TAHPCB":"17,25","TAHCYM":"17,25"},{"Dia":"05/04/2025","Hora":"07-08","PCB":"68,40","CYM":"68,40","COF2TD":"0,000075353514000000","PMHPCB":"24,95","PMHCYM":"24,95","SAHPCB":"19,56","SAHCYM":"19,56","FOMPCB":"0,05","FOMCYM":"0,05","FOSPCB":"0,20","FOSCYM":"0,20","INTPCB":"0,00","INTCYM":"0,00","PCAPPCB":"0,00","PCAPCYM":"0,00","TEUPCB":"2,99","TEUCYM":"2,99","CCVPCB":"3,48","CCVCYM":"3,48","EDSRPCB":"0,00","EDSRCYM":"0,00","TAHPCB":"17,17","TAHCYM":"17,17"},{"Dia":"05/04/2025","Hora":"08-09","PCB":"74,08","CYM":"74,08","COF2TD":"0,000086726830000000","PMHPCB":"25,63","PMHCYM":"25,63","SAHPCB":"24,74","SAHCYM":"24,74","FOMPCB":"0,05","FOMCYM":"0,05","FOSPCB":"0,20","FOSCYM":"0,20","INTPCB":"0,00","INTCYM":"0,00","PCAPPCB":"0,00","PCAPCYM":"0,00","TEUPCB":"2,99","TEUCYM":"2,99","CCVPCB":"3,53","CCVCYM":"3,53","EDSRPCB":"0,00","EDSRCYM":"0,00","TAHPCB":"16,94","TAHCYM":"16,94"},{"Dia":"05/04/2025","Hora":"09-10","PCB":"55,11","CYM":"55,11","COF2TD":"0,000106641964000000","PMHPCB":"13,47","PMHCYM":"13,47","SAHPCB":"18,54","SAHCYM":"18,54","FOMPCB":"0,05","FOMCYM":"0,05","FOSPCB":"0,20","FOSCYM":"0,20","INTPCB":"0,00","INTCYM":"0,00","PCAPPCB":"0,00","PCAPCYM":"0,00","TEUPCB":"2,99","TEUCYM":"2,99","CCVPCB":"3,21","CCVCYM":"3,21","EDSRPCB":"0,00","EDSRCYM":"0,00","TAHPCB":"16,65","TAHCYM":"16,65"},{"Dia":"05/04/2025","Hora":"10-11","PCB":"42,36","CYM":"42,36","COF2TD":"0,000119895281000000","PMHPCB":"3,24","PMHCYM":"3,24","SAHPCB":"16,46","SAHCYM":"16,46","FOMPCB":"0,05","FOMCYM":"0,05","FOSPCB":"0,19","FOSCYM":"0,19","INTPCB":"0,00","INTCYM":"0,00","PCAPPCB":"0,00","PCAPCYM":"0,00","TEUPCB":"2,99","TEUCYM":"2,99","CCVPCB":"2,98","CCVCYM":"2,98","EDSRPCB":"0,00","EDSRCYM":"0,00","TAHPCB":"16,44","TAHCYM":"16,44"},{"Dia":"05/04/2025","Hora":"11-12","PCB":"38,63","CYM":"38,63","COF2TD":"0,000122095312000000","PMHPCB":"0,33","PMHCYM":"0,33","SAHPCB":"15,84","SAHCYM":"15,84","FOMPCB":"0,05","FOMCYM":"0,05","FOSPCB":"0,19","FOSCYM":"0,19","INTPCB":"0,00","INTCYM":"0,00","PCAPPCB":"0,00","PCAPCYM":"0,00","TEUPCB":"2,99","TEUCYM":"2,99","CCVPCB":"2,91","CCVCYM":"2,91","EDSRPCB":"0,00","EDSRCYM":"0,00","TAHPCB":"16,31","TAHCYM":"16,31"},{"Dia":"05/04/2025","Hora":"12-13","PCB":"37,39","CYM":"37,39","COF2TD":"0,000122775930000000","PMHPCB":"-0,31","PMHCYM":"-0,31","SAHPCB":"15,33","SAHCYM":"15,33","FOMPCB":"0,05","FOMCYM":"0,05","FOSPCB":"0,19","FOSCYM":"0,19","INTPCB":"0,00","INTCYM":"0,00","PCAPPCB":"0,00","PCAPCYM":"0,00","TEUPCB":"2,99","TEUCYM":"2,99","CCVPCB":"2,88","CCVCYM":"2,88","EDSRPCB":"0,00","EDSRCYM":"0,00","TAHPCB":"16,25","TAHCYM":"16,25"},{"Dia":"05/04/2025","Hora":"13-14","PCB":"36,37","CYM":"36,37","COF2TD":"0,000128957231000000","PMHPCB":"-1,14","PMHCYM":"-1,14","SAHPCB":"15,22","SAHCYM":"15,22","FOMPCB":"0,05","FOMCYM":"0,05","FOSPCB":"0,19","FOSCYM":"0,19","INTPCB":"0,00","INTCYM":"0,00","PCAPPCB":"0,00","PCAPCYM":"0,00","TEUPCB":"2,99","TEUCYM":"2,99","CCVPCB":"2,86","CCVCYM":"2,86","EDSRPCB":"0,00","EDSRCYM":"0,00","TAHPCB":"16,20","TAHCYM":"16,20"},{"Dia":"05/04/2025","Hora":"14-15","PCB":"36,66","CYM":"36,66","COF2TD":"0,000129717213000000","PMHPCB":"-1,15","PMHCYM":"-1,15","SAHPCB":"15,54","SAHCYM":"15,54","FOMPCB":"0,05","FOMCYM":"0,05","FOSPCB":"0,19","FOSCYM":"0,19","INTPCB":"0,00","INTCYM":"0,00","PCAPPCB":"0,00","PCAPCYM":"0,00","TEUPCB":"2,99","TEUCYM":"2,99","CCVPCB":"2,86","CCVCYM":"2,86","EDSRPCB":"0,00","EDSRCYM":"0,00","TAHPCB":"16,18","TAHCYM":"16,18"},{"Dia":"05/04/2025","Hora":"15-16","PCB":"38,12","CYM":"38,12","COF2TD":"0,000115793233000000","PMHPCB":"-1,36","PMHCYM":"-1,36","SAHPCB":"17,02","SAHCYM":"17,02","FOMPCB":"0,05","FOMCYM":"0,05","FOSPCB":"0,19","FOSCYM":"0,19","INTPCB":"0,00","INTCYM":"0,00","PCAPPCB":"0,00","PCAPCYM":"0,00","TEUPCB":"2,99","TEUCYM":"2,99","CCVPCB":"2,90","CCVCYM":"2,90","EDSRPCB":"0,00","EDSRCYM":"0,00","TAHPCB":"16,32","TAHCYM":"16,32"},{"Dia":"05/04/2025","Hora":"16-17","PCB":"39,06","CYM":"39,06","COF2TD":"0,000106691557000000","PMHPCB":"-0,92","PMHCYM":"-0,92","SAHPCB":"17,39","SAHCYM":"17,39","FOMPCB":"0,05","FOMCYM":"0,05","FOSPCB":"0,19","FOSCYM":"0,19","INTPCB":"0,00","INTCYM":"0,00","PCAPPCB":"0,00","PCAPCYM":"0,00","TEUPCB":"2,99","TEUCYM":"2,99","CCVPCB":"2,93","CCVCYM":"2,93","EDSRPCB":"0,00","EDSRCYM":"0,00","TAHPCB":"16,42","TAHCYM":"16,42"},{"Dia":"05/04/2025","Hora":"17-18","PCB":"40,12","CYM":"40,12","COF2TD":"0,000103808124000000","PMHPCB":"0,27","PMHCYM":"0,27","SAHPCB":"16,98","SAHCYM":"16,98","FOMPCB":"0,05","FOMCYM":"0,05","FOSPCB":"0,20","FOSCYM":"0,20","INTPCB":"0,00","INTCYM":"0,00","PCAPPCB":"0,00","PCAPCYM":"0,00","TEUPCB":"2,99","TEUCYM":"2,99","CCVPCB":"2,98","CCVCYM":"2,98","EDSRPCB":"0,00","EDSRCYM":"0,00","TAHPCB":"16,65","TAHCYM":"16,65"},{"Dia":"05/04/2025","Hora":"18-19","PCB":"51,65","CYM":"51,65","COF2TD":"0,000104234334000000","PMHPCB":"12,61","PMHCYM":"12,61","SAHPCB":"15,74","SAHCYM":"15,74","FOMPCB":"0,05","FOMCYM":"0,05","FOSPCB":"0,20","FOSCYM":"0,20","INTPCB":"0,00","INTCYM":"0,00","PCAPPCB":"0,00","PCAPCYM":"0,00","TEUPCB":"2,99","TEUCYM":"2,99","CCVPCB":"3,18","CCVCYM":"3,18","EDSRPCB":"0,00","EDSRCYM":"0,00","TAHPCB":"16,87","TAHCYM":"16,87"},{"Dia":"05/04/2025","Hora":"19-20","PCB":"99,75","CYM":"99,75","COF2TD":"0,000107994344000000","PMHPCB":"57,36","PMHCYM":"57,36","SAHPCB":"18,22","SAHCYM":"18,22","FOMPCB":"0,05","FOMCYM":"0,05","FOSPCB":"0,20","FOSCYM":"0,20","INTPCB":"0,00","INTCYM":"0,00","PCAPPCB":"0,00","PCAPCYM":"0,00","TEUPCB":"2,99","TEUCYM":"2,99","CCVPCB":"3,93","CCVCYM":"3,93","EDSRPCB":"0,00","EDSRCYM":"0,00","TAHPCB":"16,99","TAHCYM":"16,99"},{"Dia":"05/04/2025","Hora":"20-21","PCB":"147,70","CYM":"147,70","COF2TD":"0,000121879476000000","PMHPCB":"113,61","PMHCYM":"113,61","SAHPCB":"9,19","SAHCYM":"9,19","FOMPCB":"0,05","FOMCYM":"0,05","FOSPCB":"0,20","FOSCYM":"0,20","INTPCB":"0,00","INTCYM":"0,00","PCAPPCB":"0,00","PCAPCYM":"0,00","TEUPCB":"2,99","TEUCYM":"2,99","CCVPCB":"4,65","CCVCYM":"4,65","EDSRPCB":"0,00","EDSRCYM":"0,00","TAHPCB":"17,01","TAHCYM":"17,01"},{"Dia":"05/04/2025","Hora":"21-22","PCB":"150,68","CYM":"150,68","COF2TD":"0,000145894436000000","PMHPCB":"113,93","PMHCYM":"113,93","SAHPCB":"11,87","SAHCYM":"11,87","FOMPCB":"0,05","FOMCYM":"0,05","FOSPCB":"0,20","FOSCYM":"0,20","INTPCB":"0,00","INTCYM":"0,00","PCAPPCB":"0,00","PCAPCYM":"0,00","TEUPCB":"2,99","TEUCYM":"2,99","CCVPCB":"4,68","CCVCYM":"4,68","EDSRPCB":"0,00","EDSRCYM":"0,00","TAHPCB":"16,95","TAHCYM":"16,95"},{"Dia":"05/04/2025","Hora":"22-23","PCB":"132,96","CYM":"132,96","COF2TD":"0,000138800518000000","PMHPCB":"95,40","PMHCYM":"95,40","SAHPCB":"12,86","SAHCYM":"12,86","FOMPCB":"0,05","FOMCYM":"0,05","FOSPCB":"0,20","FOSCYM":"0,20","INTPCB":"0,00","INTCYM":"0,00","PCAPPCB":"0,00","PCAPCYM":"0,00","TEUPCB":"2,99","TEUCYM":"2,99","CCVPCB":"4,43","CCVCYM":"4,43","EDSRPCB":"0,00","EDSRCYM":"0,00","TAHPCB":"17,02","TAHCYM":"17,02"},{"Dia":"05/04/2025","Hora":"23-24","PCB":"121,68","CYM":"121,68","COF2TD":"0,000121757284000000","PMHPCB":"83,02","PMHCYM":"83,02","SAHPCB":"14,04","SAHCYM":"14,04","FOMPCB":"0,05","FOMCYM":"0,05","FOSPCB":"0,20","FOSCYM":"0,20","INTPCB":"0,00","INTCYM":"0,00","PCAPPCB":"0,00","PCAPCYM":"0,00","TEUPCB":"2,99","TEUCYM":"2,99","CCVPCB":"4,27","CCVCYM":"4,27","EDSRPCB":"0,00","EDSRCYM":"0,00","TAHPCB":"17,11","TAHCYM":"17,11"}]}