{"PVPC":[{"Dia":"27/04/2026","Hora":"00-01","PCB":"132,14","CYM":"132,14","COF2TD":"0,000103579032000000","PMHPCB":"97,23","PMHCYM":"97,23","SAHPCB":"23,87","SAHCYM":"23,87","FOMPCB":"0,05","FOMCYM":"0,05","FOSPCB":"0,24","FOSCYM":"0,24","INTPCB":"0,00","INTCYM":"0,00","PCAPPCB":"0,00","PCAPCYM":"0,00","TEUPCB":"3,29","TEUCYM":"3,29","CCVPCB":"5,52","CCVCYM":"5,52","EDSRPCB":"0,00","EDSRCYM":"0,00","TAHPCB":"1,94","TAHCYM":"1,94"},{"Dia":"27/04/2026","Hora":"01-02","PCB":"129,35","CYM":"129,35","COF2TD":"0,000085749758000000","PMHPCB":"92,82","PMHCYM":"92,82","SAHPCB":"25,49","SAHCYM":"25,49","FOMPCB":"0,05","FOMCYM":"0,05","FOSPCB":"0,25","FOSCYM":"0,25","INTPCB":"0,00","INTCYM":"0,00","PCAPPCB":"0,00","PCAPCYM":"0,00","TEUPCB":"3,29","TEUCYM":"3,29","CCVPCB":"5,51","CCVCYM":"5,51","EDSRPCB":"0,00","EDSRCYM":"0,00","TAHPCB":"1,95","TAHCYM":"1,95"},{"Dia":"27/04/2026","Hora":"02-03","PCB":"116,83","CYM":"116,83","COF2TD":"0,000074400119000000","PMHPCB":"75,84","PMHCYM":"75,84","SAHPCB":"30,12","SAHCYM":"30,12","FOMPCB":"0,05","FOMCYM":"0,05","FOSPCB":"0,25","FOSCYM":"0,25","INTPCB":"0,00","INTCYM":"0,00","PCAPPCB":"0,00","PCAPCYM":"0,00","TEUPCB":"3,29","TEUCYM":"3,29","CCVPCB":"5,33","CCVCYM":"5,33","EDSRPCB":"0,00","EDSRCYM":"0,00","TAHPCB":"1,95","TAHCYM":"1,95"},{"Dia":"27/04/2026","Hora":"03-04","PCB":"112,17","CYM":"112,17","COF2TD":"0,000068473213000000","PMHPCB":"69,77","PMHCYM":"69,77","SAHPCB":"31,60","SAHCYM":"31,60","FOMPCB":"0,05","FOMCYM":"0,05","FOSPCB":"0,25","FOSCYM":"0,25","INTPCB":"0,00","INTCYM":"0,00","PCAPPCB":"0,00","PCAPCYM":"0,00","TEUPCB":"3,29","TEUCYM":"3,29","CCVPCB":"5,25","CCVCYM":"5,25","EDSRPCB":"0,00","EDSRCYM":"0,00","TAHPCB":"1,95","TAHCYM":"1,95"},{"Dia":"27/04/2026","Hora":"04-05","PCB":"107,49","CYM":"107,49","COF2TD":"0,000065800310000000","PMHPCB":"65,32","PMHCYM":"65,32","SAHPCB":"31,45","SAHCYM":"31,45","FOMPCB":"0,05","FOMCYM":"0,05","FOSPCB":"0,25","FOSCYM":"0,25","INTPCB":"0,00","INTCYM":"0,00","PCAPPCB":"0,00","PCAPCYM":"0,00","TEUPCB":"3,29","TEUCYM":"3,29","CCVPCB":"5,18","CCVCYM":"5,18","EDSRPCB":"0,00","EDSRCYM":"0,00","TAHPCB":"1,95","TAHCYM":"1,95"},{"Dia":"27/04/2026","Hora":"05-06","PCB":"121,70","CYM":"121,70","COF2TD":"0,000066225387000000","PMHPCB":"83,58","PMHCYM":"83,58","SAHPCB":"27,19","SAHCYM":"27,19","FOMPCB":"0,05","FOMCYM":"0,05","FOSPCB":"0,25","FOSCYM":"0,25","INTPCB":"0,00","INTCYM":"0,00","PCAPPCB":"0,00","PCAPCYM":"0,00","TEUPCB":"3,29","TEUCYM":"3,29","CCVPCB":"5,40","CCVCYM":"5,40","EDSRPCB":"0,00","EDSRCYM":"0,00","TAHPCB":"1,95","TAHCYM":"1,95"},{"Dia":"27/04/2026","Hora":"06-07","PCB":"138,58","CYM":"138,58","COF2TD":"0,000071782736000000","PMHPCB":"106,89","PMHCYM":"106,89","SAHPCB":"20,57","SAHCYM":"20,57","FOMPCB":"0,05","FOMCYM":"0,05","FOSPCB":"0,24","FOSCYM":"0,24","INTPCB":"0,00","INTCYM":"0,00","PCAPPCB":"0,00","PCAPCYM":"0,00","TEUPCB":"3,29","TEUCYM":"3,29","CCVPCB":"5,61","CCVCYM":"5,61","EDSRPCB":"0,00","EDSRCYM":"0,00","TAHPCB":"1,93","TAHCYM":"1,93"},{"Dia":"27/04/2026","Hora":"07-08","PCB":"151,60","CYM":"151,60","COF2TD":"0,000082649369000000","PMHPCB":"118,05","PMHCYM":"118,05","SAHPCB":"22,31","SAHCYM":"22,31","FOMPCB":"0,05","FOMCYM":"0,05","FOSPCB":"0,24","FOSCYM":"0,24","INTPCB":"0,00","INTCYM":"0,00","PCAPPCB":"0,00","PCAPCYM":"0,00","TEUPCB":"3,29","TEUCYM":"3,29","CCVPCB":"5,76","CCVCYM":"5,76","EDSRPCB":"0,00","EDSRCYM":"0,00","TAHPCB":"1,91","TAHCYM":"1,91"},{"Dia":"27/04/2026","Hora":"08-09","PCB":"157,77","CYM":"157,77","COF2TD":"0,000093701651000000","PMHPCB":"96,68","PMHCYM":"96,68","SAHPCB":"23,94","SAHCYM":"23,94","FOMPCB":"0,05","FOMCYM":"0,05","FOSPCB":"0,24","FOSCYM":"0,24","INTPCB":"0,00","INTCYM":"0,00","PCAPPCB":"0,16","PCAPCYM":"0,16","TEUPCB":"29,27","TEUCYM":"29,27","CCVPCB":"5,51","CCVCYM":"5,51","EDSRPCB":"0,00","EDSRCYM":"0,00","TAHPCB":"1,93","TAHCYM":"1,93"},{"Dia":"27/04/2026","Hora":"09-10","PCB":"90,31","CYM":"90,31","COF2TD":"0,000102044470000000","PMHPCB":"27,92","PMHCYM":"27,92","SAHPCB":"26,44","SAHCYM":"26,44","FOMPCB":"0,05","FOMCYM":"0,05","FOSPCB":"0,24","FOSCYM":"0,24","INTPCB":"0,00","INTCYM":"0,00","PCAPPCB":"0,15","PCAPCYM":"0,15","TEUPCB":"29,27","TEUCYM":"29,27","CCVPCB":"4,38","CCVCYM":"4,38","EDSRPCB":"0,00","EDSRCYM":"0,00","TAHPCB":"1,87","TAHCYM":"1,87"},{"Dia":"27/04/2026","Hora":"10-11","PCB":"127,93","CYM":"58,76","COF2TD":"0,000108831064000000","PMHPCB":"1,11","PMHCYM":"1,11","SAHPCB":"22,27","SAHCYM":"22,20","FOMPCB":"0,05","FOMCYM":"0,05","FOSPCB":"0,24","FOSCYM":"0,23","INTPCB":"0,00","INTCYM":"0,00","PCAPPCB":"0,93","PCAPCYM":"0,15","TEUPCB":"97,55","TEUCYM":"29,27","CCVPCB":"3,92","CCVCYM":"3,90","EDSRPCB":"0,00","EDSRCYM":"0,00","TAHPCB":"1,87","TAHCYM":"1,86"},{"Dia":"27/04/2026","Hora":"11-12","PCB":"127,37","CYM":"127,37","COF2TD":"0,000111800760000000","PMHPCB":"-0,01","PMHCYM":"-0,01","SAHPCB":"22,81","SAHCYM":"22,81","FOMPCB":"0,05","FOMCYM":"0,05","FOSPCB":"0,24","FOSCYM":"0,24","INTPCB":"0,00","INTCYM":"0,00","PCAPPCB":"0,93","PCAPCYM":"0,93","TEUPCB":"97,55","TEUCYM":"97,55","CCVPCB":"3,92","CCVCYM":"3,92","EDSRPCB":"0,00","EDSRCYM":"0,00","TAHPCB":"1,88","TAHCYM":"1,88"},{"Dia":"27/04/2026","Hora":"12-13","PCB":"127,83","CYM":"127,83","COF2TD":"0,000115828770000000","PMHPCB":"-0,13","PMHCYM":"-0,13","SAHPCB":"23,42","SAHCYM":"23,42","FOMPCB":"0,05","FOMCYM":"0,05","FOSPCB":"0,23","FOSCYM":"0,23","INTPCB":"0,00","INTCYM":"0,00","PCAPPCB":"0,92","PCAPCYM":"0,92","TEUPCB":"97,55","TEUCYM":"97,55","CCVPCB":"3,91","CCVCYM":"3,91","EDSRPCB":"0,00","EDSRCYM":"0,00","TAHPCB":"1,87","TAHCYM":"1,87"},{"Dia":"27/04/2026","Hora":"13-14","PCB":"127,01","CYM":"127,01","COF2TD":"0,000121597938000000","PMHPCB":"-0,94","PMHCYM":"-0,94","SAHPCB":"23,44","SAHCYM":"23,44","FOMPCB":"0,05","FOMCYM":"0,05","FOSPCB":"0,23","FOSCYM":"0,23","INTPCB":"0,00","INTCYM":"0,00","PCAPPCB":"0,92","PCAPCYM":"0,92","TEUPCB":"97,55","TEUCYM":"97,55","CCVPCB":"3,89","CCVCYM":"3,89","EDSRPCB":"0,00","EDSRCYM":"0,00","TAHPCB":"1,86","TAHCYM":"1,86"},{"Dia":"27/04/2026","Hora":"14-15","PCB":"59,09","CYM":"128,27","COF2TD":"0,000119437423000000","PMHPCB":"-0,58","PMHCYM":"-0,59","SAHPCB":"24,15","SAHCYM":"24,23","FOMPCB":"0,05","FOMCYM":"0,05","FOSPCB":"0,24","FOSCYM":"0,24","INTPCB":"0,00","INTCYM":"0,00","PCAPPCB":"0,16","PCAPCYM":"0,94","TEUPCB":"29,27","TEUCYM":"97,55","CCVPCB":"3,94","CCVCYM":"3,96","EDSRPCB":"0,00","EDSRCYM":"0,00","TAHPCB":"1,88","TAHCYM":"1,89"},{"Dia":"27/04/2026","Hora":"15-16","PCB":"59,89","CYM":"59,89","COF2TD":"0,000115290901000000","PMHPCB":"-0,42","PMHCYM":"-0,42","SAHPCB":"24,72","SAHCYM":"24,72","FOMPCB":"0,05","FOMCYM":"0,05","FOSPCB":"0,24","FOSCYM":"0,24","INTPCB":"0,00","INTCYM":"0,00","PCAPPCB":"0,16","PCAPCYM":"0,16","TEUPCB":"29,27","TEUCYM":"29,27","CCVPCB":"3,98","CCVCYM":"3,98","EDSRPCB":"0,00","EDSRCYM":"0,00","TAHPCB":"1,90","TAHCYM":"1,90"},{"Dia":"27/04/2026","Hora":"16-17","PCB":"60,37","CYM":"60,37","COF2TD":"0,000109548168000000","PMHPCB":"-0,07","PMHCYM":"-0,07","SAHPCB":"24,80","SAHCYM":"24,80","FOMPCB":"0,05","FOMCYM":"0,05","FOSPCB":"0,24","FOSCYM":"0,24","INTPCB":"0,00","INTCYM":"0,00","PCAPPCB":"0,16","PCAPCYM":"0,16","TEUPCB":"29,27","TEUCYM":"29,27","CCVPCB":"4,02","CCVCYM":"4,02","EDSRPCB":"0,00","EDSRCYM":"0,00","TAHPCB":"1,91","TAHCYM":"1,91"},{"Dia":"27/04/2026","Hora":"17-18","PCB":"60,26","CYM":"60,26","COF2TD":"0,000107024151000000","PMHPCB":"0,42","PMHCYM":"0,42","SAHPCB":"24,18","SAHCYM":"24,18","FOMPCB":"0,05","FOMCYM":"0,05","FOSPCB":"0,24","FOSCYM":"0,24","INTPCB":"0,00","INTCYM":"0,00","PCAPPCB":"0,16","PCAPCYM":"0,16","TEUPCB":"29,27","TEUCYM":"29,27","CCVPCB":"4,03","CCVCYM":"4,03","EDSRPCB":"0,00","EDSRCYM":"0,00","TAHPCB":"1,92","TAHCYM":"1,92"},{"Dia":"27/04/2026","Hora":"18-19","PCB":"138,62","CYM":"69,40","COF2TD":"0,000108235901000000","PMHPCB":"11,37","PMHCYM":"11,33","SAHPCB":"22,43","SAHCYM":"22,35","FOMPCB":"0,05","FOMCYM":"0,05","FOSPCB":"0,24","FOSCYM":"0,24","INTPCB":"0,00","INTCYM":"0,00","PCAPPCB":"0,94","PCAPCYM":"0,16","TEUPCB":"97,55","TEUCYM":"29,27","CCVPCB":"4,14","CCVCYM":"4,11","EDSRPCB":"0,00","EDSRCYM":"0,00","TAHPCB":"1,90","TAHCYM":"1,89"},{"Dia":"27/04/2026","Hora":"19-20","PCB":"203,98","CYM":"203,98","COF2TD":"0,000113857288000000","PMHPCB":"74,31","PMHCYM":"74,31","SAHPCB":"23,81","SAHCYM":"23,81","FOMPCB":"0,05","FOMCYM":"0,05","FOSPCB":"0,24","FOSCYM":"0,24","INTPCB":"0,00","INTCYM":"0,00","PCAPPCB":"0,95","PCAPCYM":"0,95","TEUPCB":"97,55","TEUCYM":"97,55","CCVPCB":"5,15","CCVCYM":"5,15","EDSRPCB":"0,00","EDSRCYM":"0,00","TAHPCB":"1,92","TAHCYM":"1,92"},{"Dia":"27/04/2026","Hora":"20-21","PCB":"227,91","CYM":"227,91","COF2TD":"0,000128603357000000","PMHPCB":"99,79","PMHCYM":"99,79","SAHPCB":"22,13","SAHCYM":"22,13","FOMPCB":"0,05","FOMCYM":"0,05","FOSPCB":"0,23","FOSCYM":"0,23","INTPCB":"0,00","INTCYM":"0,00","PCAPPCB":"0,92","PCAPCYM":"0,92","TEUPCB":"97,55","TEUCYM":"97,55","CCVPCB":"5,39","CCVCYM":"5,39","EDSRPCB":"0,00","EDSRCYM":"0,00","TAHPCB":"1,85","TAHCYM":"1,85"},{"Dia":"27/04/2026","Hora":"21-22","PCB":"241,50","CYM":"241,50","COF2TD":"0,000152408064000000","PMHPCB":"112,70","PMHCYM":"112,70","SAHPCB":"22,54","SAHCYM":"22,54","FOMPCB":"0,05","FOMCYM":"0,05","FOSPCB":"0,24","FOSCYM":"0,24","INTPCB":"0,00","INTCYM":"0,00","PCAPPCB":"0,93","PCAPCYM":"0,93","TEUPCB":"97,55","TEUCYM":"97,55","CCVPCB":"5,62","CCVCYM":"5,62","EDSRPCB":"0,00","EDSRCYM":"0,00","TAHPCB":"1,87","TAHCYM":"1,87"},{"Dia":"27/04/2026","Hora":"22-23","PCB":"162,82","CYM":"232,47","COF2TD":"0,000149407390000000","PMHPCB":"102,01","PMHCYM":"102,44","SAHPCB":"23,63","SAHCYM":"23,72","FOMPCB":"0,05","FOMCYM":"0,05","FOSPCB":"0,24","FOSCYM":"0,24","INTPCB":"0,00","INTCYM":"0,00","PCAPPCB":"0,16","PCAPCYM":"0,95","TEUPCB":"29,27","TEUCYM":"97,55","CCVPCB":"5,55","CCVCYM":"5,59","EDSRPCB":"0,00","EDSRCYM":"0,00","TAHPCB":"1,92","TAHCYM":"1,92"},{"Dia":"27/04/2026","Hora":"23-24","PCB":"156,78","CYM":"156,78","COF2TD":"0,000124569390000000","PMHPCB":"98,16","PMHCYM":"98,16","SAHPCB":"21,46","SAHCYM":"21,46","FOMPCB":"0,05","FOMCYM":"0,05","FOSPCB":"0,24","FOSCYM":"0,24","INTPCB":"0,00","INTCYM":"0,00","PCAPPCB":"0,16","PCAPCYM":"0,16","TEUPCB":"29,27","TEUCYM":"29,27","CCVPCB":"5,51","CCVCYM":"5,51","EDSRPCB":"0,00","EDSRCYM":"0,00","TAHPCB":"1,94","TAHCYM":"1,94"}]}