{"PVPC":[{"Dia":"18/07/2025","Hora":"00-01","PCB":"141,77","CYM":"141,77","COF2TD":"0,000120556040000000","PMHPCB":"133,21","PMHCYM":"133,21","SAHPCB":"11,25","SAHCYM":"11,25","FOMPCB":"0,05","FOMCYM":"0,05","FOSPCB":"0,20","FOSCYM":"0,20","INTPCB":"0,00","INTCYM":"0,00","PCAPPCB":"0,00","PCAPCYM":"0,00","TEUPCB":"2,99","TEUCYM":"2,99","CCVPCB":"4,51","CCVCYM":"4,51","EDSRPCB":"0,00","EDSRCYM":"0,00","TAHPCB":"-10,44","TAHCYM":"-10,44"},{"Dia":"18/07/2025","Hora":"01-02","PCB":"134,63","CYM":"134,63","COF2TD":"0,000104428952000000","PMHPCB":"125,74","PMHCYM":"125,74","SAHPCB":"11,69","SAHCYM":"11,69","FOMPCB":"0,05","FOMCYM":"0,05","FOSPCB":"0,20","FOSCYM":"0,20","INTPCB":"0,00","INTCYM":"0,00","PCAPPCB":"0,00","PCAPCYM":"0,00","TEUPCB":"2,99","TEUCYM":"2,99","CCVPCB":"4,40","CCVCYM":"4,40","EDSRPCB":"0,00","EDSRCYM":"0,00","TAHPCB":"-10,44","TAHCYM":"-10,44"},{"Dia":"18/07/2025","Hora":"02-03","PCB":"135,08","CYM":"135,08","COF2TD":"0,000092893980000000","PMHPCB":"125,31","PMHCYM":"125,31","SAHPCB":"12,57","SAHCYM":"12,57","FOMPCB":"0,05","FOMCYM":"0,05","FOSPCB":"0,20","FOSCYM":"0,20","INTPCB":"0,00","INTCYM":"0,00","PCAPPCB":"0,00","PCAPCYM":"0,00","TEUPCB":"2,99","TEUCYM":"2,99","CCVPCB":"4,41","CCVCYM":"4,41","EDSRPCB":"0,00","EDSRCYM":"0,00","TAHPCB":"-10,45","TAHCYM":"-10,45"},{"Dia":"18/07/2025","Hora":"03-04","PCB":"130,86","CYM":"130,86","COF2TD":"0,000085797330000000","PMHPCB":"123,76","PMHCYM":"123,76","SAHPCB":"9,97","SAHCYM":"9,97","FOMPCB":"0,05","FOMCYM":"0,05","FOSPCB":"0,20","FOSCYM":"0,20","INTPCB":"0,00","INTCYM":"0,00","PCAPPCB":"0,00","PCAPCYM":"0,00","TEUPCB":"2,99","TEUCYM":"2,99","CCVPCB":"4,35","CCVCYM":"4,35","EDSRPCB":"0,00","EDSRCYM":"0,00","TAHPCB":"-10,46","TAHCYM":"-10,46"},{"Dia":"18/07/2025","Hora":"04-05","PCB":"129,35","CYM":"129,35","COF2TD":"0,000081433135000000","PMHPCB":"122,32","PMHCYM":"122,32","SAHPCB":"9,91","SAHCYM":"9,91","FOMPCB":"0,05","FOMCYM":"0,05","FOSPCB":"0,20","FOSCYM":"0,20","INTPCB":"0,00","INTCYM":"0,00","PCAPPCB":"0,00","PCAPCYM":"0,00","TEUPCB":"2,99","TEUCYM":"2,99","CCVPCB":"4,32","CCVCYM":"4,32","EDSRPCB":"0,00","EDSRCYM":"0,00","TAHPCB":"-10,44","TAHCYM":"-10,44"},{"Dia":"18/07/2025","Hora":"05-06","PCB":"131,29","CYM":"131,29","COF2TD":"0,000078446845000000","PMHPCB":"124,66","PMHCYM":"124,66","SAHPCB":"9,46","SAHCYM":"9,46","FOMPCB":"0,05","FOMCYM":"0,05","FOSPCB":"0,20","FOSCYM":"0,20","INTPCB":"0,00","INTCYM":"0,00","PCAPPCB":"0,00","PCAPCYM":"0,00","TEUPCB":"2,99","TEUCYM":"2,99","CCVPCB":"4,34","CCVCYM":"4,34","EDSRPCB":"0,00","EDSRCYM":"0,00","TAHPCB":"-10,41","TAHCYM":"-10,41"},{"Dia":"18/07/2025","Hora":"06-07","PCB":"138,32","CYM":"138,32","COF2TD":"0,000075221999000000","PMHPCB":"129,31","PMHCYM":"129,31","SAHPCB":"11,71","SAHCYM":"11,71","FOMPCB":"0,05","FOMCYM":"0,05","FOSPCB":"0,20","FOSCYM":"0,20","INTPCB":"0,00","INTCYM":"0,00","PCAPPCB":"0,00","PCAPCYM":"0,00","TEUPCB":"2,99","TEUCYM":"2,99","CCVPCB":"4,44","CCVCYM":"4,44","EDSRPCB":"0,00","EDSRCYM":"0,00","TAHPCB":"-10,37","TAHCYM":"-10,37"},{"Dia":"18/07/2025","Hora":"07-08","PCB":"142,84","CYM":"142,84","COF2TD":"0,000073342976000000","PMHPCB":"132,76","PMHCYM":"132,76","SAHPCB":"12,66","SAHCYM":"12,66","FOMPCB":"0,05","FOMCYM":"0,05","FOSPCB":"0,19","FOSCYM":"0,19","INTPCB":"0,00","INTCYM":"0,00","PCAPPCB":"0,00","PCAPCYM":"0,00","TEUPCB":"2,99","TEUCYM":"2,99","CCVPCB":"4,49","CCVCYM":"4,49","EDSRPCB":"0,00","EDSRCYM":"0,00","TAHPCB":"-10,31","TAHCYM":"-10,31"},{"Dia":"18/07/2025","Hora":"08-09","PCB":"158,87","CYM":"158,87","COF2TD":"0,000080233003000000","PMHPCB":"124,10","PMHCYM":"124,10","SAHPCB":"12,02","SAHCYM":"12,02","FOMPCB":"0,05","FOMCYM":"0,05","FOSPCB":"0,19","FOSCYM":"0,19","INTPCB":"0,00","INTCYM":"0,00","PCAPPCB":"0,16","PCAPCYM":"0,16","TEUPCB":"28,20","TEUCYM":"28,20","CCVPCB":"4,32","CCVCYM":"4,32","EDSRPCB":"0,00","EDSRCYM":"0,00","TAHPCB":"-10,17","TAHCYM":"-10,17"},{"Dia":"18/07/2025","Hora":"09-10","PCB":"142,47","CYM":"142,47","COF2TD":"0,000089450547000000","PMHPCB":"102,52","PMHCYM":"102,52","SAHPCB":"17,44","SAHCYM":"17,44","FOMPCB":"0,05","FOMCYM":"0,05","FOSPCB":"0,19","FOSCYM":"0,19","INTPCB":"0,00","INTCYM":"0,00","PCAPPCB":"0,16","PCAPCYM":"0,16","TEUPCB":"28,20","TEUCYM":"28,20","CCVPCB":"4,07","CCVCYM":"4,07","EDSRPCB":"0,00","EDSRCYM":"0,00","TAHPCB":"-10,16","TAHCYM":"-10,16"},{"Dia":"18/07/2025","Hora":"10-11","PCB":"195,87","CYM":"130,35","COF2TD":"0,000097415177000000","PMHPCB":"91,50","PMHCYM":"91,17","SAHPCB":"16,90","SAHCYM":"16,84","FOMPCB":"0,05","FOMCYM":"0,05","FOSPCB":"0,19","FOSCYM":"0,19","INTPCB":"0,00","INTCYM":"0,00","PCAPPCB":"0,96","PCAPCYM":"0,16","TEUPCB":"92,54","TEUCYM":"28,20","CCVPCB":"3,91","CCVCYM":"3,89","EDSRPCB":"0,00","EDSRCYM":"0,00","TAHPCB":"-10,18","TAHCYM":"-10,15"},{"Dia":"18/07/2025","Hora":"11-12","PCB":"199,07","CYM":"199,07","COF2TD":"0,000101980765000000","PMHPCB":"93,02","PMHCYM":"93,02","SAHPCB":"18,54","SAHCYM":"18,54","FOMPCB":"0,05","FOMCYM":"0,05","FOSPCB":"0,19","FOSCYM":"0,19","INTPCB":"0,00","INTCYM":"0,00","PCAPPCB":"0,96","PCAPCYM":"0,96","TEUPCB":"92,54","TEUCYM":"92,54","CCVPCB":"3,97","CCVCYM":"3,97","EDSRPCB":"0,00","EDSRCYM":"0,00","TAHPCB":"-10,20","TAHCYM":"-10,20"},{"Dia":"18/07/2025","Hora":"12-13","PCB":"196,52","CYM":"196,52","COF2TD":"0,000108189312000000","PMHPCB":"91,07","PMHCYM":"91,07","SAHPCB":"17,98","SAHCYM":"17,98","FOMPCB":"0,05","FOMCYM":"0,05","FOSPCB":"0,19","FOSCYM":"0,19","INTPCB":"0,00","INTCYM":"0,00","PCAPPCB":"0,96","PCAPCYM":"0,96","TEUPCB":"92,54","TEUCYM":"92,54","CCVPCB":"3,93","CCVCYM":"3,93","EDSRPCB":"0,00","EDSRCYM":"0,00","TAHPCB":"-10,20","TAHCYM":"-10,20"},{"Dia":"18/07/2025","Hora":"13-14","PCB":"187,49","CYM":"187,49","COF2TD":"0,000118616441000000","PMHPCB":"83,33","PMHCYM":"83,33","SAHPCB":"16,82","SAHCYM":"16,82","FOMPCB":"0,05","FOMCYM":"0,05","FOSPCB":"0,19","FOSCYM":"0,19","INTPCB":"0,00","INTCYM":"0,00","PCAPPCB":"0,96","PCAPCYM":"0,96","TEUPCB":"92,54","TEUCYM":"92,54","CCVPCB":"3,79","CCVCYM":"3,79","EDSRPCB":"0,00","EDSRCYM":"0,00","TAHPCB":"-10,19","TAHCYM":"-10,19"},{"Dia":"18/07/2025","Hora":"14-15","PCB":"119,93","CYM":"185,41","COF2TD":"0,000126122597000000","PMHPCB":"80,81","PMHCYM":"81,10","SAHPCB":"16,95","SAHCYM":"17,01","FOMPCB":"0,05","FOMCYM":"0,05","FOSPCB":"0,19","FOSCYM":"0,19","INTPCB":"0,00","INTCYM":"0,00","PCAPPCB":"0,16","PCAPCYM":"0,96","TEUPCB":"28,20","TEUCYM":"92,54","CCVPCB":"3,73","CCVCYM":"3,76","EDSRPCB":"0,00","EDSRCYM":"0,00","TAHPCB":"-10,15","TAHCYM":"-10,19"},{"Dia":"18/07/2025","Hora":"15-16","PCB":"123,08","CYM":"123,08","COF2TD":"0,000125060618000000","PMHPCB":"82,50","PMHCYM":"82,50","SAHPCB":"18,36","SAHCYM":"18,36","FOMPCB":"0,05","FOMCYM":"0,05","FOSPCB":"0,19","FOSCYM":"0,19","INTPCB":"0,00","INTCYM":"0,00","PCAPPCB":"0,16","PCAPCYM":"0,16","TEUPCB":"28,20","TEUCYM":"28,20","CCVPCB":"3,79","CCVCYM":"3,79","EDSRPCB":"0,00","EDSRCYM":"0,00","TAHPCB":"-10,17","TAHCYM":"-10,17"},{"Dia":"18/07/2025","Hora":"16-17","PCB":"123,01","CYM":"123,01","COF2TD":"0,000124184582000000","PMHPCB":"82,62","PMHCYM":"82,62","SAHPCB":"18,19","SAHCYM":"18,19","FOMPCB":"0,05","FOMCYM":"0,05","FOSPCB":"0,19","FOSCYM":"0,19","INTPCB":"0,00","INTCYM":"0,00","PCAPPCB":"0,16","PCAPCYM":"0,16","TEUPCB":"28,20","TEUCYM":"28,20","CCVPCB":"3,79","CCVCYM":"3,79","EDSRPCB":"0,00","EDSRCYM":"0,00","TAHPCB":"-10,18","TAHCYM":"-10,18"},{"Dia":"18/07/2025","Hora":"17-18","PCB":"124,44","CYM":"124,44","COF2TD":"0,000125650748000000","PMHPCB":"83,75","PMHCYM":"83,75","SAHPCB":"18,47","SAHCYM":"18,47","FOMPCB":"0,05","FOMCYM":"0,05","FOSPCB":"0,19","FOSCYM":"0,19","INTPCB":"0,00","INTCYM":"0,00","PCAPPCB":"0,16","PCAPCYM":"0,16","TEUPCB":"28,20","TEUCYM":"28,20","CCVPCB":"3,81","CCVCYM":"3,81","EDSRPCB":"0,00","EDSRCYM":"0,00","TAHPCB":"-10,19","TAHCYM":"-10,19"},{"Dia":"18/07/2025","Hora":"18-19","PCB":"188,65","CYM":"123,16","COF2TD":"0,000127362856000000","PMHPCB":"82,72","PMHCYM":"82,43","SAHPCB":"18,64","SAHCYM":"18,58","FOMPCB":"0,05","FOMCYM":"0,05","FOSPCB":"0,19","FOSCYM":"0,19","INTPCB":"0,00","INTCYM":"0,00","PCAPPCB":"0,97","PCAPCYM":"0,16","TEUPCB":"92,54","TEUCYM":"28,20","CCVPCB":"3,83","CCVCYM":"3,81","EDSRPCB":"0,00","EDSRCYM":"0,00","TAHPCB":"-10,29","TAHCYM":"-10,25"},{"Dia":"18/07/2025","Hora":"19-20","PCB":"191,19","CYM":"191,19","COF2TD":"0,000128027767000000","PMHPCB":"84,73","PMHCYM":"84,73","SAHPCB":"19,16","SAHCYM":"19,16","FOMPCB":"0,05","FOMCYM":"0,05","FOSPCB":"0,19","FOSCYM":"0,19","INTPCB":"0,00","INTCYM":"0,00","PCAPPCB":"0,97","PCAPCYM":"0,97","TEUPCB":"92,54","TEUCYM":"92,54","CCVPCB":"3,88","CCVCYM":"3,88","EDSRPCB":"0,00","EDSRCYM":"0,00","TAHPCB":"-10,33","TAHCYM":"-10,33"},{"Dia":"18/07/2025","Hora":"20-21","PCB":"228,52","CYM":"228,52","COF2TD":"0,000128781846000000","PMHPCB":"126,94","PMHCYM":"126,94","SAHPCB":"13,76","SAHCYM":"13,76","FOMPCB":"0,05","FOMCYM":"0,05","FOSPCB":"0,20","FOSCYM":"0,20","INTPCB":"0,00","INTCYM":"0,00","PCAPPCB":"0,98","PCAPCYM":"0,98","TEUPCB":"92,54","TEUCYM":"92,54","CCVPCB":"4,45","CCVCYM":"4,45","EDSRPCB":"0,00","EDSRCYM":"0,00","TAHPCB":"-10,40","TAHCYM":"-10,40"},{"Dia":"18/07/2025","Hora":"21-22","PCB":"239,58","CYM":"239,58","COF2TD":"0,000135289345000000","PMHPCB":"138,44","PMHCYM":"138,44","SAHPCB":"13,19","SAHCYM":"13,19","FOMPCB":"0,05","FOMCYM":"0,05","FOSPCB":"0,20","FOSCYM":"0,20","INTPCB":"0,00","INTCYM":"0,00","PCAPPCB":"0,99","PCAPCYM":"0,99","TEUPCB":"92,54","TEUCYM":"92,54","CCVPCB":"4,63","CCVCYM":"4,63","EDSRPCB":"0,00","EDSRCYM":"0,00","TAHPCB":"-10,46","TAHCYM":"-10,46"},{"Dia":"18/07/2025","Hora":"22-23","PCB":"173,16","CYM":"238,83","COF2TD":"0,000141850326000000","PMHPCB":"138,31","PMHCYM":"138,79","SAHPCB":"12,08","SAHCYM":"12,12","FOMPCB":"0,05","FOMCYM":"0,05","FOSPCB":"0,20","FOSCYM":"0,20","INTPCB":"0,00","INTCYM":"0,00","PCAPPCB":"0,16","PCAPCYM":"0,99","TEUPCB":"28,20","TEUCYM":"92,54","CCVPCB":"4,60","CCVCYM":"4,63","EDSRPCB":"0,00","EDSRCYM":"0,00","TAHPCB":"-10,44","TAHCYM":"-10,48"},{"Dia":"18/07/2025","Hora":"23-24","PCB":"165,29","CYM":"165,29","COF2TD":"0,000130689850000000","PMHPCB":"129,23","PMHCYM":"129,23","SAHPCB":"13,41","SAHCYM":"13,41","FOMPCB":"0,05","FOMCYM":"0,05","FOSPCB":"0,20","FOSCYM":"0,20","INTPCB":"0,00","INTCYM":"0,00","PCAPPCB":"0,16","PCAPCYM":"0,16","TEUPCB":"28,20","TEUCYM":"28,20","CCVPCB":"4,48","CCVCYM":"4,48","EDSRPCB":"0,00","EDSRCYM":"0,00","TAHPCB":"-10,44","TAHCYM":"-10,44"}]}