[{"day":"14/04/2022","hour":0,"price":0.291,"zone":"valle"},{"day":"14/04/2022","hour":1,"price":0.266,"zone":"valle"},{"day":"14/04/2022","hour":2,"price":0.26,"zone":"valle"},{"day":"14/04/2022","hour":3,"price":0.259,"zone":"valle"},{"day":"14/04/2022","hour":4,"price":0.261,"zone":"valle"},{"day":"14/04/2022","hour":5,"price":0.267,"zone":"valle"},{"day":"14/04/2022","hour":6,"price":0.304,"zone":"valle"},{"day":"14/04/2022","hour":7,"price":0.306,"zone":"valle"},{"day":"14/04/2022","hour":8,"price":0.339,"zone":"llano"},{"day":"14/04/2022","hour":9,"price":0.323,"zone":"llano"},{"day":"14/04/2022","hour":10,"price":0.341,"zone":"punta"},{"day":"14/04/2022","hour":11,"price":0.32,"zone":"punta"},{"day":"14/04/2022","hour":12,"price":0.311,"zone":"punta"},{"day":"14/04/2022","hour":13,"price":0.316,"zone":"punta"},{"day":"14/04/2022","hour":14,"price":0.269,"zone":"llano"},{"day":"14/04/2022","hour":15,"price":0.271,"zone":"llano"},{"day":"14/04/2022","hour":16,"price":0.271,"zone":"llano"},{"day":"14/04/2022","hour":17,"price":0.282,"zone":"llano"},{"day":"14/04/2022","hour":18,"price":0.359,"zone":"punta"},{"day":"14/04/2022","hour":19,"price":0.375,"zone":"punta"},{"day":"14/04/2022","hour":20,"price":0.405,"zone":"punta"},{"day":"14/04/2022","hour":21,"price":0.393,"zone":"punta"},{"day":"14/04/2022","hour":22,"price":0.338,"zone":"llano"},{"day":"14/04/2022","hour":23,"price":0.322,"zone":"llano"}]